Workbook
Name Slicer_Year: #N/A

Sheet Financial Statement 
A1: Tata Motor's LTD
B4: =IF(ABS(B99)<=1,"ok","Error") -> ok | C4: =IF(ABS(C99)<=1,"ok","Error") -> ok | D4: =IF(ABS(D99)<=1,"ok","Error") -> ok | E4: =IF(ABS(E99)<=1,"ok","Error") -> ok | F4: =IF(ABS(F99)<=1,"ok","Error") -> ok | G4: =IF(ABS(G99)<=1,"ok","Error") -> ok | H4: =IF(ABS(H99)<=1,"ok","Error") -> ok | I4: =IF(ABS(I99)<=1,"ok","Error") -> ok | ... P4: =IF(ABS(P99)<=1,"ok","Error") -> ok
A5: All Values are In Millions | B5: 2016 | C5: 2017 | D5: 2018 | E5: 2019 | F5: 2020 | G5: 2021 | H5: 2022 | I5: 2023 | J5: 2024 | K5: 2025 | L5: 2026 | M5: 2027 | N5: 2028 | O5: 2029 | P5: 2030 | Q5: 2031 | R5: 2032 | S5: 2033 | T5: 2034 | U5: 2035 | V5: 2036 | W5: TV
A6: Revenue :
A7: Gross Revenue from operation's | B7: 277660 | C7: 274492 | D7: 295409 | E7: 301983 | F7: 261067 | G7: 249794 | H7: 278453 | I7: 345966 | J7: 437927 | K7: 439695 | L7: =(L107*L130)/10^6 -> 509842.76 | M7: =(M107*M130)/10^6 -> 565053.72 | N7: =(N107*N130)/10^6 -> 632074.93 | O7: =(O107*O130)/10^6 -> 712697.67 | P7: =(P107*P130)/10^6 -> 809031.82
A8: Other income | B8: 885 | C8: 754 | D8: 888.89 | E8: 2965 | F8: 2973 | G8: 2643 | H8: 3053 | I8: 4633 | J8: 5949 | K8: 6244 | L8: 5000 | M8: 5000 | N8: 5000 | O8: 5000 | P8: 5000
A10: Total Revenue : | B10: =B7+B8 -> 278545 | C10: =C7+C8 -> 275246 | D10: =D7+D8 -> 296297.89 | E10: =E7+E8 -> 304948 | F10: =F7+F8 -> 264040 | G10: =G7+G8 -> 252437 | H10: =H7+H8 -> 281506 | I10: =I7+I8 -> 350599 | ... P10: =P7+P8 -> 814031.82
A12: Costs
A13: Raw Materials | B13: =151065+2226+4614+3468 -> 161373 | C13: =160147-777.57 -> 159369.43 | D13: 171993 | E13: =182254-1245.53 -> 181008.47 | F13: =152968+(-297.27) -> 152670.73 | G13: =141392+(-35.16) -> 141356.84 | H13: =159598+1322 -> 160920 | I13: 208944 | J13: 249277 | K13: 241148 | L13: =L7*L136 -> 295708.8 | M13: =M7*M136 -> 327731.16 | N13: =N7*N136 -> 366603.46 | O13: =O7*O136 -> 413364.65 | P13: =P7*P136 -> 469238.46
A14: Purchase | B14: 12841 | C14: =13924+3910 -> 17834 | D14: 15903 | E14: 13258 | F14: 12228 | G14: 12250 | H14: 18374 | I14: 22306 | J14: 25043 | K14: 27802 | L14: =L7*L137 -> 25492.138 | M14: =M7*M137 -> 28252.686 | N14: =N7*N137 -> 31603.747 | O14: =O7*O137 -> 35634.883 | P14: =P7*P137 -> 40451.591
A15: Changes in stock in trade | B15: -2750 | C15: -7399 | D15: -2046.58 | E15: 2053 | F15: 2231 | G15: 4684 | H15: 1590 | I15: -4781 | J15: -1565 | K15: 2836 | L15: =L7*L138 -> 5098.4276 | M15: =M7*M138 -> 5650.5372 | N15: =N7*N138 -> 6320.7493 | O15: =O7*O138 -> 7126.9767 | P15: =P7*P138 -> 8090.3182
A16: Employee Cost | B16: 28880 | C16: =28332+4799 -> 33131 | D16: 30300.09 | E16: 33243 | F16: 30438 | G16: 27648 | H16: 30808 | I16: 33654 | J16: 42486 | K16: 47767 | L16: =L7*L139 -> 55387.618 | M16: =M7*M139 -> 61385.554 | N16: =N7*N139 -> 68666.515 | O16: =O7*O139 -> 77425.1 | P16: =P7*P139 -> 87890.522
A17: Other Expenses | B17: =55683-(16678) -> 39005 | C17: =55430-16876+3413 -> 41967 | D17: 41596 | E17: 62238 | F17: 57084 | G17: =28072-1732+5227 -> 31567 | H17: 47133 | I17: =61785+10661-18434 -> 54012 | J17: =78874+10958-26759 -> 63073 | K17: =85399-31105-84-922+10716 -> 64004 | L17: =L7*K140 -> 74215.026 | M17: =M7*L140 -> 96059.133 | N17: =N7*M140 -> 107452.74 | O17: =O7*N140 -> 121158.6 | P17: =P7*O140 -> 137535.41
A18: Vehicles or dies for own usage | B18: 0 | C18: 0 | D18: 0 | E18: 0 | F18: 0 | G18: 0 | H18: 0 | I18: 0 | J18: 0 | K18: 0 | L18: =K18 -> 0 | M18: =L18 -> 0 | N18: =M18 -> 0 | O18: =N18 -> 0 | P18: =O18 -> 0
A20: Total Cost : | B20: =SUM(B13:B18) -> 239349 | C20: =SUM(C13:C18) -> 244902.43 | D20: =SUM(D13:D18) -> 257745.51 | E20: =SUM(E13:E18) -> 291800.47 | F20: =SUM(F13:F18) -> 254651.73 | G20: =SUM(G13:G18) -> 217505.84 | H20: =SUM(H13:H18) -> 258825 | I20: =SUM(I13:I18) -> 314135 | ... P20: =SUM(P13:P18) -> 743206.3
A22: Operating Profits : | B22: =B10-B20 -> 39196 | C22: =C10-C20 -> 30343.57 | D22: =D10-D20 -> 38552.38 | E22: =E10-E20 -> 13147.53 | F22: =F10-F20 -> 9388.27 | G22: =G10-G20 -> 34931.16 | H22: =H10-H20 -> 22681 | I22: =I10-I20 -> 36464 | ... P22: =P10-P20 -> 70825.524
A24: Depriciation & Amortization | B24: 16710 | C24: 17904 | D24: 21553 | E24: 23590 | F24: 21425 | G24: 23590 | H24: 24835 | I24: 24860 | J24: 27270 | K24: 23256 | L24: =L206 -> 42737.1 | M24: =M206 -> 44555.7 | N24: =N206 -> 46374.3 | O24: =O206 -> 48192.9 | P24: =P206 -> 50011.5
A26: EBIT | B26: =B22-B24 -> 22486 | C26: =C22-C24 -> 12439.57 | D26: =D22-D24 -> 16999.38 | E26: =E22-E24 -> -10442.47 | F26: =F22-F24 -> -12036.73 | G26: =G22-G24 -> 11341.16 | H26: =H22-H24 -> -2154 | I26: =I22-I24 -> 11604 | ... P26: =P22-P24 -> 20814.024
A28: Interest | B28: 4889 | C28: 4238 | D28: 4681 | E28: 5758 | F28: 7243 | G28: 8097 | H28: 9311 | I28: 10225 | J28: 9985 | K28: 5083 | L28: =K28 -> 5083 | M28: =L28 -> 5083 | N28: =M28 -> 5083 | O28: =N28 -> 5083 | P28: =O28 -> 5083
A30: Profit Before Exceptional Item & Taxes | B30: =B26-B28 -> 17597 | C30: =C26-C28 -> 8201.57 | D30: =D26-D28 -> 12318.38 | E30: =E26-E28 -> -16200.47 | F30: =F26-F28 -> -19279.73 | G30: =G26-G28 -> 3244.16 | H30: =H26-H28 -> -11465 | I30: =I26-I28 -> 1379 | ... P30: =P26-P28 -> 15731.024
A31: Other/Exceptional Items | B31: =1817+32.2 -> 1849.2 | C31: =67.61+(1182) -> 1249.61 | D31: 1982 | E31: -29431 | F31: 2870 | G31: -13759 | H31: =9.83+(-21.47)+(-86.26)+301+428+(-2.52) -> 628.58 | I31: -1590 | J31: 977 | K31: 550 | L31: =K31 -> 550 | M31: =L31 -> 550 | N31: =M31 -> 550 | O31: =N31 -> 550 | P31: =O31 -> 550
A32: Profit before Taxes | B32: =B30-B31 -> 15747.8 | C32: =C30-C31 -> 6951.96 | D32: =D30-D31 -> 10336.38 | E32: =E30-E31 -> 13230.53 | F32: =F30-F31 -> -22149.73 | G32: =G30-G31 -> 17003.16 | H32: =H30-H31 -> -12093.58 | I32: =I30-I31 -> 2969 | ... P32: =P30-P31 -> 15181.024
A34: Taxes | B34: 3025 | C34: 3251 | D34: =3303+1038 -> 4341 | E34: 2437 | F34: 395.25 | G34: 2541 | H34: 4231 | I34: 704 | J34: 3851 | K34: 10502 | L34: =L32*L35 -> 3171.1943 | M34: =M32*M35 -> 235.78601 | N34: =N32*N35 -> 1326.1266 | O34: =O32*O35 -> 2748.467 | P34: =P32*P35 -> 4554.3073
L35: 0.3 | M35: 0.3 | N35: 0.3 | O35: 0.3 | P35: 0.3
A36: Profit Before Minority interest and Share in Associates | B36: =B32-B34 -> 12722.8 | C36: =C32-C34 -> 3700.96 | D36: =D32-D34 -> 5995.38 | E36: =E32-E34 -> 10793.53 | F36: =F32-F34 -> -22544.98 | G36: =G32-G34 -> 14462.16 | H36: =H32-H34 -> -16324.58 | I36: =I32-I34 -> 2265 | ... P36: =P32-P34 -> 10626.717
A37: Share in Associates + jv | B37: 577.67 | C37: 1493 | D37: 2278 | E37: 209.5 | F37: -1000 | G37: -378 | H37: -74.06 | I37: 336 | J37: 699 | K37: 287 | L37: =K37 -> 287 | M37: =L37 -> 287 | N37: =M37 -> 287 | O37: =N37 -> 287 | P37: =O37 -> 287
A39: Profit for the year | B39: =B36+B37 -> 13300.47 | C39: =C36+C37 -> 5193.96 | D39: =D36+D37 -> 8273.38 | E39: =E36+E37 -> 11003.03 | F39: =F36+F37 -> -23544.98 | G39: =G36+G37 -> 14084.16 | H39: =H36+H37 -> -16398.64 | I39: =I36+I37 -> 2601 | ... P39: =P36+P37 -> 10913.717
A42: Source of Funds
A44: Shareholder funds | B44: =SUM(B45:B50) -> 79385.02 | C44: =SUM(C45:C50) -> 58514.22 | D44: =SUM(D45:D50) -> 95952.22 | E44: =SUM(E45:E50) -> 60702.22 | F44: =SUM(F45:F50) -> 63890.54 | G44: =SUM(G45:G50) -> 56818 | H44: =SUM(H45:H50) -> 48831.88 | I44: =SUM(I45:I50) -> 52598 | ... P44: =SUM(P45:P50) -> 152272.72
A45: Share Capital | B45: 679.18 | C45: 679.22 | D45: 679.22 | E45: 679.22 | F45: 719.54 | G45: 765 | H45: 765.88 | I45: 766 | J45: 766.5 | K45: 736 | L45: =K45 -> 736 | M45: =L45 -> 736 | N45: =M45 -> 736 | O45: =N45 -> 736 | P45: =O45 -> 736
A46: Other equity | B46: 78273 | C46: 57382 | D46: 94748 | E46: 59500 | F46: 62358 | G46: 54480 | H46: 43795 | I46: 44555 | J46: 84151 | K46: 115408 | L46: =K46+L39 -> 123094.45 | M46: =L46+M39 -> 123931.62 | N46: =M46+N39 -> 127312.92 | O46: =N46+O39 -> 134013.01 | P46: =O46+P39 -> 144926.72
A48: Non controlling interest | B48: 432.84 | C48: 453 | D48: 525 | E48: 523 | F48: 813 | G48: 1573 | H48: 4271 | I48: 7277 | J48: 8175 | K48: 6610 | L48: =K48 -> 6610 | M48: =L48 -> 6610 | N48: =M48 -> 6610 | O48: =N48 -> 6610 | P48: =O48 -> 6610
A52: Long term Liabilities | B52: =SUM(B53:B56) -> 80705.24 | C52: =SUM(C53:C56) -> 99608 | D52: =SUM(D53:D56) -> 92176 | E52: =SUM(E53:E56) -> 101032 | F52: =SUM(F53:F56) -> 117771 | G52: =SUM(G53:G56) -> 128553 | H52: =SUM(H53:H56) -> 131004 | I52: =SUM(I53:I56) -> 128451 | ... P52: =SUM(P53:P56) -> 89204
A53: Loans | B53: 58453.74 | C53: =60629+11409 -> 72038 | D53: =61199+2739 -> 63938 | E53: =70973+2792 -> 73765 | F53: =83315+3858+5162 -> 92335 | G53: =93112+5412 -> 98524 | H53: =97843+5962 -> 103805 | I53: =88695+7568 -> 96263 | J53: =62148+7669 -> 69817 | K53: =40217+7642 -> 47859 | L53: =K53 -> 47859 | M53: =L53 -> 47859 | N53: =M53 -> 47859 | O53: =N53 -> 47859 | P53: =O53 -> 47859
A54: Other long term liabilities | B54: 9886.5 | C54: 17392 | D54: 11165 | E54: 13922 | F54: 8759 | G54: =12312+2556 -> 14868 | H54: =7353+5333 -> 12686 | I54: =9264+5822+2500 -> 17586 | J54: =12233+2547+1673 -> 16453 | K54: =15376+2464+901 -> 18741 | L54: =K54 -> 18741 | M54: =L54 -> 18741 | N54: =M54 -> 18741 | O54: =N54 -> 18741 | P54: =O54 -> 18741
A55: Long term provision | B55: 7891 | C55: 9004 | D55: 10948 | E55: 11854 | F55: 14736 | G55: 13606 | H55: 12955 | I55: 13196 | J55: 16536 | K55: 20935 | L55: =K55 -> 20935 | M55: =L55 -> 20935 | N55: =M55 -> 20935 | O55: =N55 -> 20935 | P55: =O55 -> 20935
A56: Deffered tax liabilities | B56: 4474 | C56: 1174 | D56: 6125 | E56: 1491 | F56: 1941 | G56: 1555 | H56: 1558 | I56: 1406 | J56: 1143 | K56: 1669 | L56: =K56 -> 1669 | M56: =L56 -> 1669 | N56: =M56 -> 1669 | O56: =N56 -> 1669 | P56: =O56 -> 1669
A58: Current Liabilities | B58: =SUM(B59:B66) -> 107048.07 | C58: =SUM(C59:C66) -> 115625 | D58: =SUM(D59:D66) -> 143211 | E58: =SUM(E59:E66) -> 145454.25 | F58: =SUM(F59:F66) -> 140451.75 | G58: =SUM(G59:G66) -> 157746 | H58: =SUM(H59:H66) -> 150678.59 | I58: =SUM(I59:I66) -> 155023 | ... P58: =SUM(P59:P66) -> 366853.86
A59: Tax Liabilities | B59: 723.53 | C59: 1392 | D59: 1559 | E59: 1017 | F59: 1040 | G59: 1086 | H59: 1253 | I59: 1254 | J59: 1527 | K59: 2146 | L59: =L157 -> 1784.4496 | M59: =M157 -> 1977.688 | N59: =N157 -> 2212.2623 | O59: =O157 -> 2494.4418 | P59: =P157 -> 2831.6114
A60: Short term Borrowings + Lease Liablities | B60: 11450.78 | C60: 13859 | D60: 16794 | E60: 20150 | F60: =16362+814 -> 17176 | G60: =42791+814 -> 43605 | H60: =41917+809.55 -> 42726.55 | I60: =36964+884 -> 37848 | J60: =36351+1092 -> 37443 | K60: =22282+1399 -> 23681 | L60: =L158 -> 40787.42 | M60: =M158 -> 45204.298 | N60: =N158 -> 50565.994 | O60: =O158 -> 57015.813 | P60: =P158 -> 64722.546
A61: Trade payable | B61: 57580 | C61: 57698 | D61: 72038 | E61: =68382+130.6 -> 68512.6 | F61: =63517+109.75 -> 63626.75 | G61: =67993+186 -> 68179 | H61: =59786+183.92 -> 59969.92 | I61: =316+71739 -> 72055 | J61: =87540+502 -> 88042 | K61: =93626+452 -> 94078 | L61: =L159 -> 107066.98 | M61: =M159 -> 118661.28 | N61: =N159 -> 132735.74 | O61: =O159 -> 149666.51 | P61: =P159 -> 169896.68
A62: Acceptance | B62: 3981 | C62: 4834 | D62: 4901 | E62: =3177 -> 3177 | F62: 2771 | G62: 7860 | H62: 9779 | I62: 7195 | J62: 5935 | K62: 3290 | L62: =L160 -> 10196.855 | M62: =M160 -> 11301.074 | N62: =N160 -> 12641.499 | O62: =O160 -> 14253.953 | P62: =P160 -> 16180.636
A63: Other current liabilities | B63: 21281 | C63: 6401 | D63: 7634 | E63: 9546 | F63: 8965 | G63: 10443 | H63: 11761 | I63: 11033 | J63: 12990 | K63: 13340 | L63: =L161 -> 20393.71 | M63: =M161 -> 22602.149 | N63: =N161 -> 25282.997 | O63: =O161 -> 28507.907 | P63: =P161 -> 32361.273
A64: Short term provision | B64: 5844.51 | C64: 5807 | D64: 7953 | E64: 10196 | F64: 10329 | G64: 12848 | H64: 10766 | I64: 11810 | J64: 12291 | K64: 15831 | L64: =L163 -> 15268.771 | M64: =M163 -> 16922.229 | N64: =N163 -> 18929.38 | O64: =O163 -> 21343.87 | P64: =P163 -> 24228.885
A65: Assets classified as held-for-sale | B65: 0 | C65: 0 | D65: 1065 | E65: 0 | F65: 0 | G65: 0 | H65: 3.12 | I65: 0 | J65: 0 | K65: 0 | L65: 0 | M65: 0 | N65: 0 | O65: 0 | P65: 0
A66: Other financial Liabilities | B66: 6187.25 | C66: 25634 | D66: 31267 | E66: 32855.65 | F66: 36544 | G66: 13725 | H66: 14420 | I66: 13828 | J66: 15385 | K66: 14318 | L66: =L164 -> 35688.993 | M66: =M164 -> 39553.761 | N66: =N164 -> 44245.245 | O66: =O164 -> 49888.837 | P66: =P164 -> 56632.228
A67: Total | B67: =B58+B52+B44 -> 267138.33 | C67: =C58+C52+C44 -> 273747.22 | D67: =D58+D52+D44 -> 331339.22 | E67: =E58+E52+E44 -> 307188.47 | F67: =F58+F52+F44 -> 322113.29 | G67: =G58+G52+G44 -> 343117 | H67: =H58+H52+H44 -> 330514.47 | I67: =I58+I52+I44 -> 336072 | ... P67: =P58+P52+P44 -> 608330.58
A70: Application of Funds
A72: Long term Assets | B72: =SUM(B73:B83) -> 157216.84 | C72: =SUM(C73:C83) -> 156919.02 | D72: =SUM(D73:D83) -> 195371.25 | E72: =SUM(E73:E83) -> 183757.42 | F72: =SUM(F73:F83) -> 202526 | G72: =SUM(G73:G83) -> 196231 | H72: =SUM(H73:H83) -> 183541.5 | I72: =SUM(I73:I83) -> 184547 | ... P72: =SUM(P73:P83) -> 237026.5
A73: Tangiable Assets | B73: 64927 | C73: 59594 | D73: 73867 | E73: 72619 | F73: 77882 | G73: 79640 | H73: 80900 | I73: 76641 | J73: 73124 | K73: 72536 | L73: =SUM(K73:K77,L204)-L206 -> 171114.9 | M73: =SUM(L73:L77,M204)-M206 -> 178389.3 | N73: =SUM(M73:M77,N204)-N206 -> 185663.7 | O73: =SUM(N73:N77,O204)-O206 -> 192938.1 | P73: =SUM(O73:O77,P204)-P206 -> 200212.5
A74: Intangiable Assets | B74: =41544.89+759.8 -> 42304.69 | C74: =35676+673 -> 36349 | D74: =47429+116.45 -> 47545.45 | E74: =37866+747 -> 38613 | F74: =42171+777 -> 42948 | G74: =51773+803 -> 52576 | H74: =50462+807 -> 51269 | I74: =840+46796 -> 47636 | J74: =39241+860 -> 40101 | K74: =33790+895 -> 34685
A75: Capital Work in progress | B75: 6550.97 | C75: 10186 | D75: 16142 | E75: 8538 | F75: 8599 | G75: 8377 | H75: 3529 | I75: 5219 | J75: 10937 | K75: 17624
A76: Intangiable Assets Under development | B76: 19367.97 | C76: 23512 | D76: 23890 | E76: 23345 | F76: 27022 | G76: 12586 | H76: 6722 | I76: 9054 | J76: 24761 | K76: 48182
A77: Right to use of asset (Finance receivable) | B77: 9671.55 | C77: 10753 | D77: 15479 | E77: 22073 | F77: =6275+16833 -> 23108 | G77: =16846+6490 -> 23336 | H77: =6686+11135 -> 17821 | I77: =7801+7416 -> 15217 | J77: =8059+6094 -> 14153 | K77: 8476
A78: Non-current Investment | B78: =3763.95+770 -> 4533.95 | C78: =4606+690.76 -> 5296.76 | D78: =4887+763.9 -> 5650.9 | E78: =4743+1497 -> 6240 | F78: =1028+4418 -> 5446 | G78: =4200+1368 -> 5568 | H78: =4349+2320 -> 6669 | I78: =4675+2865 -> 7540 | J78: =5340+3377 -> 8717 | K78: =5534+2923 -> 8457 | L78: =K78 -> 8457 | M78: =L78 -> 8457 | N78: =M78 -> 8457 | O78: =N78 -> 8457 | P78: =O78 -> 8457
A79: Other financial Assets | B79: 1825 | C79: 2911 | D79: 4563 | E79: 2809 | F79: 4749 | G79: 6197 | H79: =5179-94 -> 5085 | I79: 7153 | J79: 9084 | K79: 12185 | L79: =K79 -> 12185 | M79: =L79 -> 12185 | N79: =M79 -> 12185 | O79: =N79 -> 12185 | P79: =O79 -> 12185
A80: Long term Loans and advances | B80: 503.88 | C80: 753 | D80: 495 | E80: 407.42 | F80: 782 | G80: 1034 | H80: 843 | I80: 745 | J80: 441 | K80: 99 | L80: =K80 -> 99 | M80: =L80 -> 99 | N80: =M80 -> 99 | O80: =N80 -> 99 | P80: =O80 -> 99
A81: Other Non Current Assets | B81: 2309.02 | C81: 2847 | D81: 2681 | E81: 2938 | F81: 5381 | G81: 1394 | H81: 5639 | I81: 8602 | J81: 5720 | K81: 6852 | L81: =K81 -> 6852 | M81: =L81 -> 6852 | N81: =M81 -> 6852 | O81: =N81 -> 6852 | P81: =O81 -> 6852
A82: Non Current tax | B82: 1265.81 | C82: 260.26 | D82: 899.9 | E82: 1024 | F82: 1152 | G82: 1003 | H82: =1196-1.5 -> 1194.5 | I82: 1556 | J82: 2129 | K82: 2045 | L82: =K82 -> 2045 | M82: =L82 -> 2045 | N82: =M82 -> 2045 | O82: =N82 -> 2045 | P82: =O82 -> 2045
A83: Deffered tax | B83: 3957 | C83: 4457 | D83: 4158 | E83: 5151 | F83: 5457 | G83: 4520 | H83: 3870 | I83: 5184 | J83: 13099 | K83: 7176 | L83: =K83 -> 7176 | M83: =L83 -> 7176 | N83: =M83 -> 7176 | O83: =N83 -> 7176 | P83: =O83 -> 7176
A86: Current Assets | B86: =SUM(B88:B97) -> 109921.31 | C86: =SUM(C88:C97) -> 116827.94 | D86: =SUM(D88:D97) -> 135967.91 | E86: =SUM(E88:E97) -> 123431.05 | F86: =SUM(F88:F97) -> 119586.48 | G86: =SUM(G88:G97) -> 146886 | H86: =SUM(H88:H97) -> 146972.84 | I86: =SUM(I88:I97) -> 151524.26 | ... K86: =SUM(K88:K97) -> 160325 | L86: =SUM(L88:L96) -> 242902.73 | M86: =SUM(M88:M97) -> 261500.8 | N86: =SUM(N88:N97) -> 287998.33 | O86: =SUM(O88:O97) -> 323982.24 | P86: =SUM(P88:P97) -> 371304.08
A88: Inventories | B88: 32602 | C88: 35085 | D88: 42137 | E88: 39013 | F88: 37456 | G88: 36088 | H88: 35240 | I88: 40755 | J88: 47788 | K88: 47269 | L88: =L147 -> 76476.413 | M88: =M147 -> 84758.059 | N88: =N147 -> 94811.24 | O88: =O147 -> 106904.65 | P88: =P147 -> 121354.77
A89: Receivable | B89: =13570.91+6079.92 -> 19650.83 | C89: =14075+6810 -> 20885 | D89: =19893+8401 -> 28294 | E89: =18996+11511 -> 30507 | F89: =14245+11172 -> 25417 | G89: =12679+17868 -> 30547 | H89: =12442+22095 -> 34537 | I89: =15737+23417 -> 39154 | J89: =16951+24069 -> 41020 | K89: 13248 | L89: =L148 -> 66279.558 | M89: =M148 -> 73456.984 | N89: =N148 -> 82169.741 | O89: =O148 -> 92650.697 | P89: =P148 -> 105174.14
A90: Cash & cash equivelent | B90: =17153+13306 -> 30459 | C90: =13986+22091 -> 36077 | D90: =14716+19897 -> 34613 | E90: =21559+11089 -> 32648 | F90: =18467+15259 -> 33726 | G90: =31700+15092 -> 46792 | H90: =38159+2510 -> 40669 | I90: =31886+5128 -> 37014 | J90: =40014+5791 -> 45805 | K90: =34349+6485 -> 40834 | L90: =L219 -> 37961.753 | M90: =M219 -> 34366.726 | N90: =N219 -> 33923.807 | O90: =O219 -> 37499.875 | P90: =P219 -> 46098.378
A91: Loans & Advances | B91: 1170 | C91: 710 | D91: 2279 | E91: 1268 | F91: 935.25 | G91: 1610 | H91: 1671 | I91: 123 | J91: 196 | K91: 72 | L91: =L149 -> 1835.4339 | M91: =M149 -> 2034.1934 | N91: =N149 -> 2275.4698 | O91: =O149 -> 2565.7116 | P91: =P149 -> 2912.5146
A92: Other current assets | B92: 5824 | C92: 6539 | D92: 7662 | E92: 6862 | F92: 6264 | G92: 6298 | H92: 7565 | I92: 9587 | J92: 10429 | K92: 11794 | L92: =L150 -> 10196.855 | M92: =M150 -> 11301.074 | N92: =N150 -> 12641.499 | O92: =O150 -> 14253.953 | P92: =P150 -> 16180.636
A93: Current assets tax | B93: 146.75 | C93: 935 | D93: 208.91 | E93: 184 | F93: 142.8 | G93: 865 | H93: 259.84 | I93: 259.26 | J93: 101.15 | K93: 411 | L93: =L151 -> 611.81131 | M93: =M151 -> 678.06447 | N93: =N151 -> 758.48992 | O93: =O151 -> 855.2372 | P93: =P151 -> 970.83819
A94: Investment | B94: 19233 | C94: 15041 | D94: =14663+497 -> 15160 | E94: =8938+591.05 -> 9529.05 | F94: 10861 | G94: 19051 | H94: 22709 | I94: 18838 | J94: 14253 | K94: 27199 | L94: =L152 -> 40787.42 | M94: =M152 -> 45204.298 | N94: =N152 -> 50565.994 | O94: =O152 -> 57015.813 | P94: =P152 -> 64722.546
A95: Assets classified as held-for-sale | B95: 0 | C95: 0 | D95: 2585 | E95: 162 | F95: 194.43 | G95: 220 | H95: 523 | I95: 828 | J95: 675 | K95: 514 | L95: =L166*L177 -> 596.00218 | M95: =M166*M177 -> 660.54336 | N95: =N166*N177 -> 738.89063 | O95: =O166*O177 -> 833.13797 | P95: =P166*P177 -> 945.75184
A96: Other financial assets | B96: 835.73 | C96: 1555.94 | D96: 3029 | E96: 3258 | F96: 4590 | G96: 5415 | H96: 3799 | I96: 4966 | J96: 8121 | K96: 18984 | L96: =L154 -> 8157.4841 | M96: =M154 -> 9040.8596 | N96: =N154 -> 10113.199 | O96: =O154 -> 11403.163 | P96: =P154 -> 12944.509
A98: Total | B98: =B86+B72 -> 267138.15 | C98: =C86+C72 -> 273746.96 | D98: =D86+D72 -> 331339.16 | E98: =E86+E72 -> 307188.47 | F98: =F86+F72 -> 322112.48 | G98: =G86+G72 -> 343117 | H98: =H86+H72 -> 330514.34 | I98: =I86+I72 -> 336071.26 | ... P98: =P86+P72 -> 608330.58
A99: Balance Sheet check >> | B99: =B98-B67 -> -0.18 | C99: =C98-C67 -> -0.26 | D99: =D98-D67 -> -0.06 | E99: =E98-E67 -> 0 | F99: =F98-F67 -> -0.81 | G99: =G98-G67 -> 0 | H99: =H98-H67 -> -0.13 | I99: =I98-I67 -> -0.74 | ... P99: =P98-P67 -> 0
A102: Capacity | B102: 2500000 | C102: 2600000 | D102: 2620000 | E102: 2330000 | F102: 2420000 | G102: 2450000 | H102: 2510000 | I102: 2520000 | J102: 2650000 | K102: 2700000 | L102: =K102+L103 -> 2820000 | M102: =L102+M103 -> 2940000 | N102: =M102+N103 -> 3060000 | O102: =N102+O103 -> 3180000 | P102: =O102+P103 -> 3300000
A103: New Capacity | C103: =C102-B102 -> 100000 | D103: =D102-C102 -> 20000 | E103: =E102-D102 -> -290000 | F103: =F102-E102 -> 90000 | G103: =G102-F102 -> 30000 | H103: =H102-G102 -> 60000 | I103: =I102-H102 -> 10000 | J103: =J102-I102 -> 130000 | K103: =K102-J102 -> 50000 | L103: 120000 | M103: 120000 | N103: 120000 | O103: 120000 | P103: 120000
A105: Domestic | B105: 988000 | C105: 1088000 | D105: 1189000 | E105: 1235000 | F105: 1027659 | G105: 974000 | H105: 1081000 | I105: 1281000 | J105: 1381733 | K105: 1530000 | L105: =L119*L126 -> 1598983.7 | M105: =M119*M126 -> 1719086.1 | N105: =N119*N126 -> 1867888.4 | O105: =O119*O126 -> 2048469.9 | P105: =P119*P126 -> 2264468
A106: Exports | B106: 420000 | C106: 490000 | D106: 475000 | E106: 460000 | F106: 400000 | G106: 350000 | H106: 295000 | I106: 330000 | J106: 335000 | K106: 340000 | L106: =L120*L127 -> 538197.92 | M106: =M120*M127 -> 616685.11 | N106: =N120*N127 -> 706618.36 | O106: =O120*O127 -> 809666.87 | P106: =P120*P127 -> 927743.29
A107: Total | B107: =SUM(B105:B106) -> 1408000 | C107: =SUM(C105:C106) -> 1578000 | D107: =SUM(D105:D106) -> 1664000 | E107: =SUM(E105:E106) -> 1695000 | F107: =SUM(F105:F106) -> 1427659 | G107: =SUM(G105:G106) -> 1324000 | H107: =SUM(H105:H106) -> 1376000 | I107: =SUM(I105:I106) -> 1611000 | ... K107: =SUM(K105:K106) -> 1870000 | L107: =L121*L128 -> 2125818.4 | M107: =M121*M128 -> 2309827.1 | N107: =N121*N128 -> 2533133.8 | O107: =O121*O128 -> 2800236.6 | P107: =P121*P128 -> 3116411.7
A110: Capacity Utilization | B110: =B107/B102 -> 0.5632 | C110: =C107/C102 -> 0.60692308 | D110: =D107/D102 -> 0.6351145 | E110: =E107/E102 -> 0.72746781 | F110: =F107/F102 -> 0.58994174 | G110: =G107/G102 -> 0.54040816 | H110: =H107/H102 -> 0.54820717 | I110: =I107/I102 -> 0.63928571 | ... P110: =P107/P102 -> 0.94436718
A113: Growth in Domestic Sales | C113: =C105/B105 -> 1.1012146 | D113: =D105/C105 -> 1.0928309 | E113: =E105/D105 -> 1.038688 | F113: =F105/E105 -> 0.83211255 | G113: =G105/F105 -> 0.94778521 | H113: =H105/G105 -> 1.1098563 | I113: =I105/H105 -> 1.1850139 | J113: =J105/I105 -> 1.0786362 | ... P113: =P105/O105 -> 1.1054436
A114: Growth in Export Sales | C114: =C106/B106 -> 1.1666667 | D114: =D106/C106 -> 0.96938776 | E114: =E106/D106 -> 0.96842105 | F114: =F106/E106 -> 0.86956522 | G114: =G106/F106 -> 0.875 | H114: =H106/G106 -> 0.84285714 | I114: =I106/H106 -> 1.1186441 | J114: =J106/I106 -> 1.0151515 | ... P114: =P106/O106 -> 1.1458333
A115: Growth in Total Sales | C115: =C107/B107 -> 1.1207386 | D115: =D107/C107 -> 1.0544994 | E115: =E107/D107 -> 1.0186298 | F115: =F107/E107 -> 0.8422767 | G115: =G107/F107 -> 0.92739233 | H115: =H107/G107 -> 1.0392749 | I115: =I107/H107 -> 1.1707849 | J115: =J107/I107 -> 1.0656319 | ... P115: =P107/O107 -> 1.1129101
A118: Industry Data
A119: Domestic Sales | B119: 2900000 | C119: 3100000 | D119: 3300000 | E119: 3400000 | F119: 2770000 | G119: 2710000 | H119: 3070000 | I119: 3890000 | J119: 4100000 | K119: 4300000 | L119: =K119*(1+K122) -> 4568524.7 | M119: =L119*(1+L122) -> 4911674.5 | N119: =M119*(1+M122) -> 5336824.1 | O119: =N119*(1+N122) -> 5852771.2 | P119: =O119*(1+O122) -> 6469908.6
A120: Exports | B120: 565000 | C120: 758000 | D120: 748000 | E120: 677000 | F120: 662000 | G120: 402000 | H120: 578000 | I120: 663000 | J120: 672000 | K120: 770000 | L120: =K120*(K123+1) -> 882291.67 | M120: =L120*(L123+1) -> 1010959.2 | N120: =M120*(M123+1) -> 1158390.8 | O120: =N120*(N123+1) -> 1327322.7 | P120: =O120*(O123+1) -> 1520890.6
A121: Total | B121: =SUM(B119:B120) -> 3465000 | C121: =SUM(C119:C120) -> 3858000 | D121: =SUM(D119:D120) -> 4048000 | E121: =SUM(E119:E120) -> 4077000 | F121: =SUM(F119:F120) -> 3432000 | G121: =SUM(G119:G120) -> 3112000 | H121: =SUM(H119:H120) -> 3648000 | I121: =SUM(I119:I120) -> 4553000 | ... P121: =SUM(P119:P120) -> 7990799.2
A122: Growth in Domestic Market | C122: =C121/B121-1 -> 0.11341991 | D122: =D121/C121-1 -> 0.049248315 | E122: =E121/D121-1 -> 0.0071640316 | F122: =F121/E121-1 -> -0.15820456 | G122: =G121/F121-1 -> -0.093240093 | H122: =H121/G121-1 -> 0.1722365 | I122: =I121/H121-1 -> 0.24808114 | J122: =J121/I121-1 -> 0.048100154 | ... P122: =P121/O121-1 -> 0.11291013
A123: Growth in Export | C123: =C120/B120-1 -> 0.34159292 | D123: =D120/C120-1 -> -0.013192612 | E123: =E120/D120-1 -> -0.094919786 | F123: =F120/E120-1 -> -0.022156573 | G123: =G120/F120-1 -> -0.39274924 | H123: =H120/G120-1 -> 0.43781095 | I123: =I120/H120-1 -> 0.14705882 | J123: =J120/I120-1 -> 0.013574661 | ... P123: =P120/O120-1 -> 0.14583333
A125: Market Share
A126: Domestic | B126: =B105/B119 -> 0.34068966 | C126: =C105/C119 -> 0.35096774 | D126: =D105/D119 -> 0.36030303 | E126: =E105/E119 -> 0.36323529 | F126: =F105/F119 -> 0.37099603 | G126: =G105/G119 -> 0.35940959 | H126: =H105/H119 -> 0.35211726 | I126: =I105/I119 -> 0.32930591 | ... K126: =K105/K119 -> 0.35581395 | L126: 0.35 | M126: 0.35 | N126: 0.35 | O126: 0.35 | P126: 0.35
A127: Exports | B127: =B106/B120 -> 0.74336283 | C127: =C106/C120 -> 0.64643799 | D127: =D106/D120 -> 0.63502674 | E127: =E106/E120 -> 0.67946824 | F127: =F106/F120 -> 0.60422961 | G127: =G106/G120 -> 0.87064677 | H127: =H106/H120 -> 0.51038062 | I127: =I106/I120 -> 0.49773756 | ... K127: =K106/K120 -> 0.44155844 | L127: 0.61 | M127: 0.61 | N127: 0.61 | O127: 0.61 | P127: 0.61
A128: Overall | B128: =B107/B121 -> 0.40634921 | C128: =C107/C121 -> 0.40902022 | D128: =D107/D121 -> 0.41106719 | E128: =E107/E121 -> 0.41574687 | F128: =F107/F121 -> 0.41598456 | G128: =G107/G121 -> 0.42544987 | H128: =H107/H121 -> 0.37719298 | I128: =I107/I121 -> 0.35383264 | ... K128: =K107/K121 -> 0.36883629 | L128: 0.39 | M128: 0.39 | N128: 0.39 | O128: 0.39 | P128: 0.39
A130: Revenue Per Car | B130: =(B7/B107)*1000000 -> 197201.7 | C130: =(C7/C107)*1000000 -> 173949.3 | D130: =(D7/D107)*1000000 -> 177529.45 | E130: =(E7/E107)*1000000 -> 178161.06 | F130: =(F7/F107)*1000000 -> 182863.7 | G130: =(G7/G107)*1000000 -> 188666.16 | H130: =(H7/H107)*1000000 -> 202364.1 | I130: =(I7/I107)*1000000 -> 214752.33 | ... K130: =(K7/K107)*1000000 -> 235131.02 | L130: =K130*(1+L131) -> 239833.64 | M130: =L130*(1+M131) -> 244630.31 | N130: =M130*(1+N131) -> 249522.92 | O130: =N130*(1+O131) -> 254513.37 | P130: =O130*(1+P131) -> 259603.64
A131: Growth | C131: =C130/B130-1 -> -0.11791177 | D131: =D130/C130-1 -> 0.020581538 | E131: =E130/D130-1 -> 0.0035578032 | F131: =F130/E130-1 -> 0.026395403 | G131: =G130/F130-1 -> 0.03173111 | H131: =H130/G130-1 -> 0.072604093 | I131: =I130/H130-1 -> 0.061217523 | J131: =J130/I130-1 -> 0.18784859 | K131: =K130/J130-1 -> -0.078254653 | L131: 0.02 | M131: 0.02 | N131: 0.02 | O131: 0.02 | P131: 0.02
A134: Cost Drivers
A136: Raw Materiels | B136: =B13/B7 -> 0.58118922 | C136: =C13/C7 -> 0.58059772 | D136: =D13/D7 -> 0.58221991 | E136: =E13/E7 -> 0.59939954 | F136: =F13/F7 -> 0.58479521 | G136: =G13/G7 -> 0.56589366 | H136: =H13/H7 -> 0.57790722 | I136: =I13/I7 -> 0.60394374 | ... K136: =K13/K7 -> 0.54844381 | L136: 0.58 | M136: =L136 -> 0.58 | N136: =M136 -> 0.58 | O136: =N136 -> 0.58 | P136: =O136 -> 0.58
A137: Purchases | B137: =B14/B7 -> 0.046247209 | C137: =C14/C7 -> 0.064970928 | D137: =D14/D7 -> 0.053833837 | E137: =E14/E7 -> 0.043903134 | F137: =F14/F7 -> 0.046838551 | G137: =G14/G7 -> 0.049040409 | H137: =H14/H7 -> 0.065986001 | I137: =I14/I7 -> 0.064474544 | ... K137: =K14/K7 -> 0.063230194 | L137: 0.05 | M137: =L137 -> 0.05 | N137: =M137 -> 0.05 | O137: =N137 -> 0.05 | P137: =O137 -> 0.05
A138: Change in Stock in trade | B138: =B15/B7 -> -0.0099041994 | C138: =C15/C7 -> -0.026955248 | D138: =D15/D7 -> -0.0069279541 | E138: =E15/E7 -> 0.0067983959 | F138: =F15/F7 -> 0.008545699 | G138: =G15/G7 -> 0.018751451 | H138: =H15/H7 -> 0.0057101198 | I138: =I15/I7 -> -0.013819277 | ... K138: =K15/K7 -> 0.0064499255 | L138: 0.01 | M138: 0.01 | N138: 0.01 | O138: 0.01 | P138: 0.01
A139: Employee cost | B139: =B16/B7 -> 0.1040121 | C139: =C16/C7 -> 0.12069933 | D139: =D16/D7 -> 0.10256996 | E139: =E16/E7 -> 0.11008236 | F139: =F16/F7 -> 0.11659076 | G139: =G16/G7 -> 0.1106832 | H139: =H16/H7 -> 0.11063986 | I139: =I16/I7 -> 0.097275455 | ... K139: =K16/K7 -> 0.10863667 | L139: =K139 -> 0.10863667 | M139: =L139 -> 0.10863667 | N139: =M139 -> 0.10863667 | O139: =N139 -> 0.10863667 | P139: =O139 -> 0.10863667
A140: Other Expenses | B140: =B17/B7 -> 0.14047756 | C140: =C17/C7 -> 0.1528897 | D140: =D17/D7 -> 0.14080817 | E140: =E17/E7 -> 0.20609769 | F140: =F17/F7 -> 0.21865651 | G140: =G17/G7 -> 0.12637213 | H140: =H17/H7 -> 0.16926734 | I140: =I17/I7 -> 0.15611939 | ... K140: =K17/K7 -> 0.14556454 | L140: 0.17 | M140: 0.17 | N140: 0.17 | O140: 0.17 | P140: 0.17
A141: own uses Vehicles | B141: =B18/B7 -> 0 | C141: =C18/C7 -> 0 | D141: =D18/D7 -> 0 | E141: =E18/E7 -> 0 | F141: =F18/F7 -> 0 | G141: =G18/G7 -> 0 | H141: =H18/H7 -> 0 | I141: =I18/I7 -> 0 | ... P141: =P18/P7 -> 0
...

Sheet Dashboard
B5: Connecting Aspiration's
B32: Revenue
B35: Net Profit
B38: EBITDA

Sheet Sheet2
A3: Row Labels | B3: Sum of Total Revenue
A4: 2016 | B4: 278545
A5: 2017 | B5: 275246
A6: 2018 | B6: 296297.89
A7: 2019 | B7: 304948
A8: 2020 | B8: 264040
A9: 2021 | B9: 252437
A10: 2022 | B10: 281506
A11: 2023 | B11: 350599
A12: 2024 | B12: 443876
A13: 2025 | B13: 445939
A14: 2026 | B14: 514842.76
A15: 2027 | B15: 570053.72
... A18: 2030 | B18: 814031.82
A19: Grand Total | B19: 6447134.8

Sheet KPI Cards
B3: Sum of Total Revenue
B4: 3699639.9 | D4: Row Labels | E4: Sum of Net Profit | G4: Row Labels | H4: Sum of Total Cost
D5: 2025 | E5: 22991 | G5: 2025 | H5: 383557
B6: Sum of Total Cost | D6: 2026 | E6: 19549.748 | G6: 2026 | H6: 455902.01
B7: 3337101.8 | D7: 2027 | E7: 550.16737 | G7: 2027 | H7: 519079.07
D8: 2028 | E8: 3094.2955 | G8: 2028 | H8: 580647.21
B9: Net Profit Margin | D9: 2029 | E9: 6413.0896 | G9: 2029 | H9: 654710.21
B10: 0.017089506 | D10: 2030 | E10: 10626.717 | G10: 2030 | H10: 743206.3
D11: Grand Total | E11: 63225.017 | G11: Grand Total | H11: 3337101.8
B13: Return on equity
B14: 0.077790253
B16: Debt to Equity
B17: 0.026649303
B20: Interest coverage ratio
B21: 0.041606566
B23: Current Ratio
B24: 0.010105972

Sheet Return on equity 
B3: Row Labels | C3: Return on equity
B4: 2025 | C4: 0.18729329
B5: 2026 | C5: 0.14987488
B6: 2027 | C6: 0.0041908694
B7: 2028 | C7: 0.022978764
B8: 2029 | C8: 0.045367393
B9: 2030 | C9: 0.069787397
B10: Grand Total | C10: 0.077790253

Sheet Debt to Equity 
B3: Row Labels | C3: Debt to Equity
B4: 2025 | C4: 0.020845594
B5: 2026 | C5: 0.024562256
B6: 2027 | C6: 0.026312671
B7: 2028 | C7: 0.027908818
B8: 2029 | C8: 0.029172201
B9: 2030 | C9: 0.029950069
B10: Grand Total | C10: 0.026649303

Sheet Net Profit Margin
B3: Row Labels | C3: Net Profit Margin
B4: 2025 | C4: 0.051556379
B5: 2026 | C5: 0.037972269
B6: 2027 | C6: 0.00096511494
B7: 2028 | C7: 0.0048570353
B8: 2029 | C8: 0.0089356423
B9: 2030 | C9: 0.013054425
B10: Grand Total | C10: 0.017089506

Sheet Interest coverage ratio
B3: Row Labels | C3: Interest coverage ratio
B4: 2025 | C4: 0.076974228
B5: 2026 | C5: 0.070204107
B6: 2027 | C6: 0.012628277
B7: 2028 | C7: 0.019778521
B8: 2029 | C8: 0.029105954
B9: 2030 | C9: 0.040948307
B10: Grand Total | C10: 0.041606566

Sheet Cash Flow For the year
B3: Row Labels | C3: Sum of Cash flow
B4: 2025 | C4: 40834
B5: 2026 | C5: 37961.753
B6: 2027 | C6: 34366.726
B7: 2028 | C7: 33923.807
B8: 2029 | C8: 37499.875
B9: 2030 | C9: 46098.378
B10: Grand Total | C10: 230684.54

Sheet EBITDA per Year 
B3: Row Labels | C3: Sum of Operating Profit
B4: 2025 | C4: 62382
B5: 2026 | C5: 58940.748
B6: 2027 | C6: 50974.653
B7: 2028 | C7: 56427.722
B8: 2029 | C8: 62987.457
B9: 2030 | C9: 70825.524
B10: Grand Total | C10: 362538.1

Sheet Profit for the Year
B3: Row Labels | C3: Sum of Net Profit
B4: 2025 | C4: 22991
B5: 2026 | C5: 19549.748
B6: 2027 | C6: 550.16737
B7: 2028 | C7: 3094.2955
B8: 2029 | C8: 6413.0896
B9: 2030 | C9: 10626.717
B10: Grand Total | C10: 63225.017

Sheet Expense By Tata Motors (2)
B3: Row Labels | C3: Sum of Total Cost
B4: 2025 | C4: 383557
B5: 2026 | C5: 455902.01
B6: 2027 | C6: 519079.07
B7: 2028 | C7: 580647.21
B8: 2029 | C8: 654710.21
B9: 2030 | C9: 743206.3
B10: Grand Total | C10: 3337101.8

Sheet Revenue By Tata Motors
B3: Row Labels | C3: Sum of Total Revenue
B4: 2025 | C4: 445939
B5: 2026 | C5: 514842.76
B6: 2027 | C6: 570053.72
B7: 2028 | C7: 637074.93
B8: 2029 | C8: 717697.67
B9: 2030 | C9: 814031.82
B10: Grand Total | C10: 3699639.9

Sheet Supporting schedule for Dashboa
A1: Year | B1: Total Revenue | C1: Total Cost | D1: Operating Profit | E1: Depricition & Amortization | F1: EBIT | G1: Interest | H1: Profit Before Exceptional item | I1: Exceptional item | J1: Tax | K1: Net Profit | L1: Total Equity | M1: Total Current Liabilities | N1: Total Long term liabilities | O1: Total Liabilites | P1: Total Liability & Equity | Q1: Total Current Asset | R1: Total Long term Assets | S1: Total Asset | T1: Check | U1: Capacity | V1: New Capacity | W1: Export | X1: Domestic | Y1: Total | Z1: Capacity Utilization | AA1: Working capital | AB1: Capex Schedule | AC1: Assets per Car | AD1: Cash flow
A2: 2025 | B2: ='Financial Statement '!K10 -> 445939 | C2: ='Financial Statement '!K20 -> 383557 | D2: =B2-C2 -> 62382 | E2: ='Financial Statement '!K24 -> 23256 | F2: =D2-E2 -> 39126 | G2: ='Financial Statement '!K28 -> 5083 | H2: =F2-G2 -> 34043 | I2: ='Financial Statement '!K31 -> 550 | J2: ='Financial Statement '!K34 -> 10502 | K2: =H2-I2-J2 -> 22991 | L2: ='Financial Statement '!K44 -> 122754 | M2: ='Financial Statement '!K58 -> 166684 | N2: ='Financial Statement '!K52 -> 89204 | O2: =M2+N2 -> 255888 | P2: =O2+L2 -> 378642 | Q2: ='Financial Statement '!K86 -> 160325 | R2: ='Financial Statement '!K72 -> 218317 | S2: =Q2+R2 -> 378642 | T2: =S2-P2 -> 0 | U2: ='Financial Statement '!K102 -> 2700000 | V2: =U2-#REF! -> #REF! | W2: ='Financial Statement '!K106 -> 340000 | X2: ='Financial Statement '!K105 -> 1530000 | Y2: =W2+X2 -> 1870000 | Z2: =Y2/U2 -> 0.69259259 | AA2: =Q2-M2 -> -6359 | AB2: ='Financial Statement '!K197 -> 176064 | AC2: =AB2/U2*10^6 -> 65208.889 | AD2: ='Financial Statement '!K90 -> 40834
A3: 2026 | B3: ='Financial Statement '!L10 -> 514842.76 | C3: ='Financial Statement '!L20 -> 455902.01 | D3: =B3-C3 -> 58940.748 | E3: ='Financial Statement '!K24 -> 23256 | F3: =D3-E3 -> 35684.748 | G3: ='Financial Statement '!L28 -> 5083 | H3: =F3-G3 -> 30601.748 | I3: ='Financial Statement '!K31 -> 550 | J3: ='Financial Statement '!K34 -> 10502 | K3: =H3-I3-J3 -> 19549.748 | L3: ='Financial Statement '!L44 -> 130440.45 | M3: ='Financial Statement '!L58 -> 231187.18 | N3: ='Financial Statement '!L52 -> 89204 | O3: =M3+N3 -> 320391.18 | P3: =O3+L3 -> 450831.63 | Q3: ='Financial Statement '!L86 -> 242902.73 | R3: ='Financial Statement '!L72 -> 207928.9 | S3: =Q3+R3 -> 450831.63 | T3: =S3-P3 -> 0 | U3: ='Financial Statement '!L102 -> 2820000 | V3: =U3-U2 -> 120000 | W3: ='Financial Statement '!L106 -> 538197.92 | X3: ='Financial Statement '!L105 -> 1598983.7 | Y3: =W3+X3 -> 2137181.6 | Z3: =Y3/U3 -> 0.75786581 | AA3: =Q3-M3 -> 11715.553 | AB3: ='Financial Statement '!L197 -> 213685.5 | AC3: =AB3/U3*10^6 -> 75775 | AD3: ='Financial Statement '!L90 -> 37961.753
A4: 2027 | B4: ='Financial Statement '!M10 -> 570053.72 | C4: ='Financial Statement '!M20 -> 519079.07 | D4: =B4-C4 -> 50974.653 | E4: ='Financial Statement '!M24 -> 44555.7 | F4: =D4-E4 -> 6418.9534 | G4: ='Financial Statement '!M28 -> 5083 | H4: =F4-G4 -> 1335.9534 | I4: ='Financial Statement '!M31 -> 550 | J4: ='Financial Statement '!M34 -> 235.78601 | K4: =H4-I4-J4 -> 550.16737 | L4: ='Financial Statement '!M44 -> 131277.62 | M4: ='Financial Statement '!M58 -> 256222.48 | N4: ='Financial Statement '!M52 -> 89204 | O4: =M4+N4 -> 345426.48 | P4: =O4+L4 -> 476704.1 | Q4: ='Financial Statement '!M86 -> 261500.8 | R4: ='Financial Statement '!M72 -> 215203.3 | S4: =Q4+R4 -> 476704.1 | T4: =S4-P4 -> 0 | U4: ='Financial Statement '!M102 -> 2940000 | V4: =U4-U3 -> 120000 | W4: ='Financial Statement '!M106 -> 616685.11 | X4: ='Financial Statement '!M105 -> 1719086.1 | Y4: =W4+X4 -> 2335771.2 | Z4: =Y4/U4 -> 0.79447999 | AA4: =Q4-M4 -> 5278.3208 | AB4: ='Financial Statement '!M197 -> 222778.5 | AC4: =AB4/U4*10^6 -> 75775 | AD4: ='Financial Statement '!M90 -> 34366.726
A5: 2028 | B5: ='Financial Statement '!N10 -> 637074.93 | C5: ='Financial Statement '!N20 -> 580647.21 | D5: =B5-C5 -> 56427.722 | E5: ='Financial Statement '!N24 -> 46374.3 | F5: =D5-E5 -> 10053.422 | G5: ='Financial Statement '!N28 -> 5083 | H5: =F5-G5 -> 4970.4221 | I5: ='Financial Statement '!N31 -> 550 | J5: ='Financial Statement '!N34 -> 1326.1266 | K5: =H5-I5-J5 -> 3094.2955 | L5: ='Financial Statement '!N44 -> 134658.92 | M5: ='Financial Statement '!N58 -> 286613.11 | N5: ='Financial Statement '!N52 -> 89204 | O5: =M5+N5 -> 375817.11 | P5: =O5+L5 -> 510476.03 | Q5: ='Financial Statement '!N86 -> 287998.33 | R5: ='Financial Statement '!N72 -> 222477.7 | S5: =Q5+R5 -> 510476.03 | T5: =S5-P5 -> 0 | U5: ='Financial Statement '!N102 -> 3060000 | V5: =U5-U4 -> 120000 | W5: ='Financial Statement '!N106 -> 706618.36 | X5: ='Financial Statement '!N105 -> 1867888.4 | Y5: =W5+X5 -> 2574506.8 | Z5: =Y5/U5 -> 0.84134209 | AA5: =Q5-M5 -> 1385.2163 | AB5: ='Financial Statement '!N197 -> 231871.5 | AC5: =AB5/U5*10^6 -> 75775 | AD5: ='Financial Statement '!N90 -> 33923.807
A6: 2029 | B6: ='Financial Statement '!O10 -> 717697.67 | C6: ='Financial Statement '!O20 -> 654710.21 | D6: =B6-C6 -> 62987.457 | E6: ='Financial Statement '!O24 -> 48192.9 | F6: =D6-E6 -> 14794.557 | G6: ='Financial Statement '!O28 -> 5083 | H6: =F6-G6 -> 9711.5566 | I6: ='Financial Statement '!O31 -> 550 | J6: ='Financial Statement '!O34 -> 2748.467 | K6: =H6-I6-J6 -> 6413.0896 | L6: ='Financial Statement '!O44 -> 141359.01 | M6: ='Financial Statement '!O58 -> 323171.33 | N6: ='Financial Statement '!O52 -> 89204 | O6: =M6+N6 -> 412375.33 | P6: =O6+L6 -> 553734.34 | Q6: ='Financial Statement '!O86 -> 323982.24 | R6: ='Financial Statement '!O72 -> 229752.1 | S6: =Q6+R6 -> 553734.34 | T6: =S6-P6 -> 0 | U6: ='Financial Statement '!O102 -> 3180000 | V6: =U6-U5 -> 120000 | W6: ='Financial Statement '!O106 -> 809666.87 | X6: ='Financial Statement '!O105 -> 2048469.9 | Y6: =W6+X6 -> 2858136.8 | Z6: =Y6/U6 -> 0.89878515 | AA6: =Q6-M6 -> 810.90592 | AB6: ='Financial Statement '!O197 -> 240964.5 | AC6: =AB6/U6*10^6 -> 75775 | AD6: ='Financial Statement '!O90 -> 37499.875
A7: 2030 | B7: ='Financial Statement '!P10 -> 814031.82 | C7: ='Financial Statement '!P20 -> 743206.3 | D7: =B7-C7 -> 70825.524 | E7: ='Financial Statement '!P24 -> 50011.5 | F7: =D7-E7 -> 20814.024 | G7: ='Financial Statement '!P28 -> 5083 | H7: =F7-G7 -> 15731.024 | I7: ='Financial Statement '!P31 -> 550 | J7: ='Financial Statement '!P34 -> 4554.3073 | K7: =H7-I7-J7 -> 10626.717 | L7: ='Financial Statement '!P44 -> 152272.72 | M7: ='Financial Statement '!P58 -> 366853.86 | N7: ='Financial Statement '!P52 -> 89204 | O7: =M7+N7 -> 456057.86 | P7: =O7+L7 -> 608330.58 | Q7: ='Financial Statement '!P86 -> 371304.08 | R7: ='Financial Statement '!P72 -> 237026.5 | S7: =Q7+R7 -> 608330.58 | T7: =S7-P7 -> 0 | U7: ='Financial Statement '!P102 -> 3300000 | V7: =U7-U6 -> 120000 | W7: ='Financial Statement '!P106 -> 927743.29 | X7: ='Financial Statement '!P105 -> 2264468 | Y7: =W7+X7 -> 3192211.3 | Z7: =Y7/U7 -> 0.96733675 | AA7: =Q7-M7 -> 4450.2229 | AB7: ='Financial Statement '!P197 -> 250057.5 | AC7: =AB7/U7*10^6 -> 75775 | AD7: ='Financial Statement '!P90 -> 46098.378
A9: Year
A10: 2025
A11: 2026
A12: 2027
A13: 2028
A14: 2029
A15: 2030
