Workbook
Name Slicer_Year: #N/A

Sheet Financial Statement 
A1: Balance sheet check >> | B1: =IF(ABS(B93)<=1,"ok","Error") -> ok | C1: =IF(ABS(C93)<=1,"ok","Error") -> ok | D1: =IF(ABS(D93)<=1,"ok","Error") -> ok | E1: =IF(ABS(E93)<=1,"ok","Error") -> ok | F1: =IF(ABS(F93)<=1,"ok","Error") -> ok | G1: =IF(ABS(G93)<=1,"ok","Error") -> ok | H1: =IF(ABS(H93)<=1,"ok","Error") -> ok | I1: =IF(ABS(I93)<=1,"ok","Error") -> ok | ... P1: =IF(ABS(P93)<=1,"ok","Error") -> ok
A2: All Values are in MI | B2: 2016 | C2: 2017 | D2: 2018 | E2: 2019 | F2: 2020 | G2: 2021 | H2: 2022 | I2: 2023 | J2: 2024 | K2: 2025 | L2: 2026 | M2: 2027 | N2: 2028 | O2: 2029 | P2: 2030 | Q2: 2031 | R2: 2032 | S2: 2033 | T2: 2034 | U2: 2035 | V2: 2036 | W2: Terminal Value
A4: Revenue
A5: Gross Revenue From Operation | B5: 570615 | C5: 680850 | D5: 798094 | E5: 860685 | F5: 756600 | G5: 703720 | H5: 883298 | I5: 1184099 | J5: 1418582 | K5: =K101*K125/10^6 -> 1750571.8 | L5: =L101*L125/10^6 -> 2051120.2 | M5: =M101*M125/10^6 -> 2404139.8 | N5: =N101*N125/10^6 -> 2818896 | O5: =O101*O125/10^6 -> 3306302.3 | P5: =P101*P125/10^6 -> 3879215.2
A6: Other Income | B6: 15505 | C6: 22896 | D6: 20458 | E6: 25616 | F6: 33344 | G6: 29363 | H6: 17447 | I6: 22647 | J6: 40935 | K6: 20000 | L6: =K6 -> 20000 | M6: =L6 -> 20000 | N6: =M6 -> 20000 | O6: =N6 -> 20000 | P6: =O6 -> 20000
A8: Total Revenue | B8: =B5+B6 -> 586120 | C8: =C5+C6 -> 703746 | D8: =D5+D6 -> 818552 | E8: =E5+E6 -> 886301 | F8: =F5+F6 -> 789944 | G8: =G5+G6 -> 733083 | H8: =H5+H6 -> 900745 | I8: =I5+I6 -> 1206746 | ... P8: =P5+P6 -> 3899215.2
A10: Cost
A11: Raw Materials | B11: 362007 | C11: 426279 | D11: 449432 | E11: 450257 | F11: 346348 | G11: 332964 | H11: 397396 | I11: 733522 | J11: 789153 | K11: =K5*K130 -> 1050343.1 | L11: =L5*L130 -> 1230672.1 | M11: =M5*M130 -> 1442483.9 | N11: =N5*N130 -> 1691337.6 | O11: =O5*O130 -> 1983781.4 | P11: =P5*P130 -> 2327529.1
A12: Purchases | B12: 31715 | C12: 44936 | D12: 100021 | E12: 143209 | F12: 187672 | G12: 172541 | H12: 263975 | I12: 127147 | J12: 212042 | K12: =K5*K131 -> 140045.75 | L12: =L5*L131 -> 164089.61 | M12: =M5*M131 -> 192331.19 | N12: =N5*N131 -> 225511.68 | O12: =O5*O131 -> 264504.18 | P12: =P5*P131 -> 310337.21
A13: Changes in Stock in trade | B13: 63 | C13: -3793 | D13: 408 | E13: 2116 | F13: -2378 | G13: 2736 | H13: -931 | I13: -5805 | J13: -3786 | K13: =K5*K132 -> -4672.0351 | L13: =L5*L132 -> -5474.1572 | M13: =M5*M132 -> -6416.3181 | N13: =N5*N132 -> -7523.2452 | O13: =O5*O132 -> -8824.0654 | P13: =P5*P132 -> -10353.091
A14: Employee Cost | B14: 20602 | C14: 23603 | D14: 28634 | E14: 32850 | F14: 34162 | G14: 34316 | H14: 40514 | I14: 53085 | J14: 63016 | K14: =K5*K133 -> 70022.873 | L14: =L5*L133 -> 82044.807 | M14: =M5*M133 -> 96165.593 | N14: =N5*N133 -> 112755.84 | O14: =O5*O133 -> 132252.09 | P14: =P5*P133 -> 155168.61
A15: Others expenses | B15: 81147 | C15: 87280 | D15: 99956 | E15: 123442 | F15: 118896 | G15: 108375 | H15: 126727 | I15: 146771 | J15: 175501 | K15: =K5*K134 -> 217070.91 | L15: =L5*L134 -> 254338.9 | M15: =M5*M134 -> 298113.34 | N15: =N5*N134 -> 349543.1 | O15: =O5*O134 -> 409981.48 | P15: =P5*P134 -> 481022.68
A16: Vehicles or Dies for Own Usage | B16: -602 | C16: -1036 | D16: -991 | E16: -1221 | F16: -1217 | G16: -728 | H16: -1445 | I16: -1565 | J16: -2607 | K16: =K5*K135 -> -3217.1145 | L16: =L5*L135 -> -3769.4474 | M16: =M5*M135 -> -4418.2095 | N16: =N5*N135 -> -5180.428 | O16: =O5*O135 -> -6076.1592 | P16: =P5*P135 -> -7129.0302
A18: Total Costs | B18: =SUM(B11:B16) -> 494932 | C18: =SUM(C11:C16) -> 577269 | D18: =SUM(D11:D16) -> 677460 | E18: =SUM(E11:E16) -> 750653 | F18: =SUM(F11:F16) -> 683483 | G18: =SUM(G11:G16) -> 650204 | H18: =SUM(H11:H16) -> 826236 | I18: =SUM(I11:I16) -> 1053155 | ... P18: =SUM(P11:P16) -> 3256575.5
A20: Operating Profit | B20: =B8-B18 -> 91188 | C20: =C8-C18 -> 126477 | D20: =D8-D18 -> 141092 | E20: =E8-E18 -> 135648 | F20: =F8-F18 -> 106461 | G20: =G8-G18 -> 82879 | H20: =H8-H18 -> 74509 | I20: =I8-I18 -> 153591 | ... P20: =P8-P18 -> 642639.69
A22: Depriciation & Amortization | B22: 28670 | C22: 26039 | D22: 27598 | E22: 30208 | F22: 35284 | G22: 30341 | H22: 27890 | I22: 48460 | J22: 52558 | K22: =K191 -> 60235.688 | L22: =L191 -> 67322.24 | M22: =M191 -> 74408.791 | N22: =N191 -> 81495.343 | O22: =O191 -> 88581.894 | P22: =P191 -> 95668.446
A24: EBIT | B24: =B20-B22 -> 62518 | C24: =C20-C22 -> 100438 | D24: =D20-D22 -> 113494 | E24: =E20-E22 -> 105440 | F24: =F20-F22 -> 71177 | G24: =G20-G22 -> 52538 | H24: =H20-H22 -> 46619 | I24: =I20-I22 -> 105131 | ... P24: =P20-P22 -> 546971.24
A26: Interest | B26: 937 | C26: 894 | D26: 3458 | E26: 759 | F26: 1342 | G26: 1018 | H26: 1266 | I26: 2523 | J26: 1936 | K26: =J26 -> 1936 | L26: =K26 -> 1936 | M26: =L26 -> 1936 | N26: =M26 -> 1936 | O26: =N26 -> 1936 | P26: =O26 -> 1936
A28: Profit Before Exceptional Items and taxes | B28: =B24-B26 -> 61581 | C28: =C24-C26 -> 99544 | D28: =D24-D26 -> 110036 | E28: =E24-E26 -> 104681 | F28: =F24-F26 -> 69835 | G28: =G24-G26 -> 51520 | H28: =H24-H26 -> 45353 | I28: =I24-I26 -> 102608 | ... P28: =P24-P26 -> 545035.24
A29: Others / Exceptional Items
A30: Profit Before Taxes | B30: =SUM(B28:B29) -> 61581 | C30: =SUM(C28:C29) -> 99544 | D30: =SUM(D28:D29) -> 110036 | E30: =SUM(E28:E29) -> 104681 | F30: =SUM(F28:F29) -> 69835 | G30: =SUM(G28:G29) -> 51520 | H30: =SUM(H28:H29) -> 45353 | I30: =SUM(I28:I29) -> 102608 | ... P30: =SUM(P28:P29) -> 545035.24
A32: Taxes | B32: 19987 | C32: 26162 | D32: 32862 | E32: 29732 | F32: 14252 | G32: 9319 | H32: 8177 | I32: 21745 | J32: 39363 | K32: =K30*K33 -> 59701.667 | L32: =L30*L33 -> 69990.028 | M32: =M30*M33 -> 82383.887 | N32: =N30*N33 -> 97255.027 | O32: =O30*O33 -> 115041.37 | P32: =P30*P33 -> 136258.81
K33: 0.25 | L33: 0.25 | M33: 0.25 | N33: 0.25 | O33: 0.25 | P33: 0.25
A34: Profit Before Minoriy Interest and Share in Associates | B34: =B30-B32 -> 41594 | C34: =C30-C32 -> 73382 | D34: =D30-D32 -> 77174 | E34: =E30-E32 -> 74949 | F34: =F30-F32 -> 55583 | G34: =G30-G32 -> 42201 | H34: =H30-H32 -> 37176 | I34: =I30-I32 -> 80863 | ... P34: =P30-P32 -> 408776.43
A35: Shares in Associates + JV | B35: 679 | C35: 2216 | D35: 3311 | E35: 1557 | F35: 1184 | G35: 1690 | H35: 1619 | I35: 1774 | J35: 2541 | K35: =J35 -> 2541 | L35: =K35 -> 2541 | M35: =L35 -> 2541 | N35: =M35 -> 2541 | O35: =N35 -> 2541 | P35: =O35 -> 2541
A37: Profit For the Year | B37: =B34+B35 -> 42273 | C37: =C34+C35 -> 75598 | D37: =D34+D35 -> 80485 | E37: =E34+E35 -> 76506 | F37: =F34+F35 -> 56767 | G37: =G34+G35 -> 43891 | H37: =H34+H35 -> 38795 | I37: =I34+I35 -> 82637 | ... P37: =P34+P35 -> 411317.43
A39: Source of Funds
A41: Shareholders Funds | B41: =SUM(B42:B47) -> 306304 | C41: =SUM(C42:C47) -> 370905 | D41: =SUM(D42:D47) -> 425755 | E41: =SUM(E42:E47) -> 471097 | F41: 494322 | G41: =SUM(G42:G47) -> 525006 | H41: =SUM(H42:H47) -> 553335 | I41: =SUM(I42:I47) -> 746002 | J41: =SUM(J42:J47) -> 856360 | K41: =SUM(K42:K47) -> 1038006 | L41: =SUM(L42:L47) -> 1250517.1 | M41: =SUM(M42:M47) -> 1500209.7 | N41: =SUM(N42:N47) -> 1794515.8 | ... P41: =SUM(P42:P47) -> 2553498.4
A42: Share Capital | B42: 1510 | C42: 1510 | D42: 1510 | E42: 1510 | F42: 1510 | G42: 1510 | H42: 1510 | I42: 1572 | J42: 1572 | K42: =J42 -> 1572 | L42: =K42 -> 1572 | M42: =L42 -> 1572 | N42: =M42 -> 1572 | O42: =N42 -> 1572 | P42: =O42 -> 1572
A43: Reserves & Surplus | B43: 304650 | C43: 369241 | D43: 424084 | E43: 469411 | F43: 492620 | G43: 523496 | H43: 551825 | I43: 744430 | J43: 854788 | K43: =J43+K37 -> 1036434 | L43: =K43+L37 -> 1248945.1 | M43: =L43+M37 -> 1498637.7 | N43: =M43+N37 -> 1792943.8 | O43: =N43+O37 -> 2140608.9 | P43: =O43+P37 -> 2551926.4
A44: Money Received Against Warrants | B44: 0 | C44: 0 | D44: 0 | E44: 0 | H44: 0 | I44: 0 | J44: 0 | K44: =J44 -> 0 | L44: =K44 -> 0 | M44: =L44 -> 0 | N44: =M44 -> 0 | O44: =N44 -> 0 | P44: =O44 -> 0
A46: Minority Interest | B46: 144 | C46: 154 | D46: 161 | E46: 176 | F46: 192 | G46: 0 | H46: 0 | I46: 0 | J46: 0 | K46: =J46 -> 0 | L46: =K46 -> 0 | M46: =L46 -> 0 | N46: =M46 -> 0 | O46: =N46 -> 0 | P46: =O46 -> 0
A47: Share Application Money Pending Allotment | B47: 0 | C47: 0 | D47: 0 | E47: 0 | F47: 0 | G47: 0 | H47: 0 | I47: 0 | J47: 0 | K47: =J47 -> 0 | L47: =K47 -> 0 | M47: =L47 -> 0 | N47: =M47 -> 0 | O47: =N47 -> 0 | P47: =O47 -> 0
A49: Long Term Liabilities | B49: =SUM(B50:B53) -> 10510 | C49: =SUM(C50:C53) -> 16332 | D49: =SUM(D50:D53) -> 22244 | E49: =SUM(E50:E53) -> 26985 | F49: =SUM(F50:F53) -> 28901 | G49: =SUM(G50:G53) -> 26616 | H49: =SUM(H50:H53) -> 22985 | I49: =SUM(I50:I53) -> 30185 | ... P49: =SUM(P50:P53) -> 37630
A50: Loans | B50: 0 | C50: 0 | D50: 100 | E50: 80 | F50: 652 | G50: 420 | H50: 329 | I50: 250 | J50: 677 | K50: =J50 -> 677 | L50: =K50 -> 677 | M50: =L50 -> 677 | N50: =M50 -> 677 | O50: =N50 -> 677 | P50: =O50 -> 677
A51: Other Long term Liabilities | B51: 8075 | C51: 11055 | D51: 15859 | E51: 20371 | F51: 21158 | G51: 21295 | H51: 21812 | I51: 25850 | J51: 31617 | K51: =J51 -> 31617 | L51: =K51 -> 31617 | M51: =L51 -> 31617 | N51: =M51 -> 31617 | O51: =N51 -> 31617 | P51: =O51 -> 31617
A52: Long term Provision | B52: 148 | C52: 219 | D52: 265 | E52: 395 | F52: 516 | G52: 447 | H52: 844 | I52: 875 | J52: 1448 | K52: =J52 -> 1448 | L52: =K52 -> 1448 | M52: =L52 -> 1448 | N52: =M52 -> 1448 | O52: =N52 -> 1448 | P52: =O52 -> 1448
A53: Deffered Taxes Liabilities | B53: 2287 | C53: 5058 | D53: 6020 | E53: 6139 | F53: 6575 | G53: 4454 | H53: 0 | I53: 3210 | J53: 3888 | K53: =J53 -> 3888 | L53: =K53 -> 3888 | M53: =L53 -> 3888 | N53: =M53 -> 3888 | O53: =N53 -> 3888 | P53: =O53 -> 3888
A55: Current Liabilties | B55: =SUM(B56:B62) -> 110441 | C55: =SUM(C56:C62) -> 132368 | D55: =SUM(D56:D62) -> 154485 | E55: =SUM(E56:E62) -> 141605 | F55: =SUM(F56:F62) -> 113054 | G55: =SUM(G56:G62) -> 162139 | H55: =SUM(H56:H62) -> 170235 | I55: =SUM(I56:I62) -> 227667 | ... P55: =SUM(P56:P62) -> 735034.85
A56: Tax Liabilities | B56: 7956 | C56: 8036 | D56: 8541 | E56: 6729 | F56: 6962 | G56: 8547 | H56: 11113 | I56: 11584 | J56: 12030 | K56: =K149 -> 14845.373 | L56: =L149 -> 17394.113 | M56: =M149 -> 20387.825 | N56: =N149 -> 23905.082 | O56: =O149 -> 28038.433 | P56: =P149 -> 32896.906
A57: Short Term Borrowings + Lease Lib | B57: 774 | C57: 4838 | D57: 1108 | E57: 1496 | F57: 1063 | G57: 4962 | H57: 3819 | I57: 12226 | J57: 509 | K57: =K150 -> 1750.5718 | L57: =L150 -> 2051.1202 | M57: =M150 -> 2404.1398 | N57: =N150 -> 2818.896 | O57: =O150 -> 3306.3023 | P57: =P150 -> 3879.2152
A58: Trade Payable Macro | B58: 74089 | C58: 83692 | D58: 104993 | E58: 96377 | F58: 75091 | G58: 101681 | H58: 97732 | I58: 1947 | J58: 2070
A59: Trade Payable Macro | B59: 0 | C59: 0 | D59: 0 | E59: 0 | F59: 0 | G59: 0 | H59: 0 | I59: 134808 | J59: 167814 | K59: =K151 -> 210068.62 | L59: =L151 -> 246134.42 | M59: =M151 -> 288496.78 | N59: =N151 -> 338267.52 | O59: =O151 -> 396756.27 | P59: =P151 -> 465505.82
A60: Others Current Liabilities | B60: 11650 | C60: 18278 | D60: 20896 | E60: 16329 | F60: 14091 | G60: 26801 | H60: 28686 | I60: 33372 | J60: 41739 | K60: =K152 -> 52517.155 | L60: =L152 -> 61533.605 | M60: =M152 -> 72124.195 | N60: =N152 -> 84566.88 | O60: =O152 -> 99189.068 | P60: =P152 -> 116376.46
A61: Short Term provision | B61: 3994 | C61: 4496 | D61: 5609 | E61: 6254 | F61: 6807 | G61: 7428 | H61: 8613 | I61: 10830 | J61: 13119 | K61: =K153 -> 17505.718 | L61: =L153 -> 20511.202 | M61: =M153 -> 24041.398 | N61: =N153 -> 28188.96 | O61: =O153 -> 33063.023 | P61: =P153 -> 38792.152
A62: Other Financial Liabilities | B62: 11978 | C62: 13028 | D62: 13338 | E62: 14420 | F62: 9040 | G62: 12720 | H62: 20272 | I62: 22900 | J62: 22237 | K62: =K154 -> 35011.437 | L62: =L154 -> 41022.403 | M62: =M154 -> 48082.796 | N62: =N154 -> 56377.92 | O62: =O154 -> 66126.045 | P62: =P154 -> 77584.304
A63: Total | B63: =B55+B49+B41 -> 427255 | C63: =C55+C49+C41 -> 519605 | D63: =D55+D49+D41 -> 602484 | E63: =E55+E49+E41 -> 639687 | F63: =F55+F49+F41 -> 636277 | G63: =G55+G49+G41 -> 713761 | H63: =H55+H49+H41 -> 746555 | I63: =I55+I49+I41 -> 1003854 | ... P63: =P55+P49+P41 -> 3326163.2
A65: Application of Funds
A67: Long-term Assets | B67: =SUM(B68:B78) -> 347744 | C67: =SUM(C68:C78) -> 431625 | D67: =SUM(D68:D78) -> 523184 | E67: =SUM(E68:E78) -> 515960 | F67: =SUM(F68:F78) -> 551871 | G67: =SUM(G68:G78) -> 532791 | H67: =SUM(H68:H78) -> 578621 | I67: =SUM(I68:I78) -> 847162 | ... P67: =SUM(P68:P78) -> 1172059.6
A68: Tangible Assets | B68: 121827 | C68: 129377 | D68: 130771 | E68: 149862 | F68: 147905 | G68: 141785 | H68: 128261 | I68: 268028 | J68: 267982 | K68: =SUM(J68:J72,K189)-K191 -> 396318.31 | L68: =SUM(K68:K72,L189)-L191 -> 437231.76 | M68: =SUM(L68:L72,M189)-M191 -> 478145.21 | N68: =SUM(M68:M72,N189)-N191 -> 519058.66 | O68: =SUM(N68:N72,O189)-O191 -> 559972.11 | P68: =SUM(O68:O72,P189)-P191 -> 600885.55
A69: Intangible Assets | B69: 3469 | C69: 3730 | D69: 3117 | E69: 4511 | F69: 4067 | G69: 2242 | H69: 3499 | I69: 5479 | J69: 4537
A70: Capital Work in progress | B70: 10069 | C70: 12523 | D70: 21321 | E70: 16069 | F70: 13443 | G70: 11993 | H70: 26462 | I70: 40541 | J70: 75043
A71: Intangible Assets Under Develo[ment | B71: 0 | C71: 0 | D71: 0 | E71: 0 | F71: 0 | G71: 2975 | H71: 2903 | I71: 889 | J71: 2305
A72: Right to use of Assets | B72: 0 | C72: 0 | D72: 0 | E72: 0 | F72: 6181 | G72: 5860 | H72: 5712 | I72: 5907 | J72: 6129
A73: Non-Currrent Investment | B73: 195345 | C73: 269718 | D73: 349058 | E73: 324581 | F73: 362692 | G73: 345291 | H73: 379348 | I73: 491843 | J73: 533838 | K73: =J73 -> 533838 | L73: =K73 -> 533838 | M73: =L73 -> 533838 | N73: =M73 -> 533838 | O73: =N73 -> 533838 | P73: =O73 -> 533838
A74: Other Financial Assets | B74: 234 | C74: 241 | D74: 328 | E74: 344 | F74: 365 | G74: 369 | H74: 375 | I74: 2398 | J74: 2981 | K74: =J74 -> 2981 | L74: =K74 -> 2981 | M74: =L74 -> 2981 | N74: =M74 -> 2981 | O74: =N74 -> 2981 | P74: =O74 -> 2981
A75: Long-term Loans and Advances | B75: 4 | C75: 3 | D75: 2 | E75: 2 | F75: 2 | G75: 2 | H75: 5446 | I75: 2 | J75: 1 | K75: =J75 -> 1 | L75: =K75 -> 1 | M75: =L75 -> 1 | N75: =M75 -> 1 | O75: =N75 -> 1 | P75: =O75 -> 1
A76: Other Non Current Assets | B76: 16796 | C76: 16033 | D76: 18587 | E76: 20591 | F76: 17216 | G76: 16867 | H76: 1411 | I76: 23226 | J76: 28049 | K76: =J76 -> 28049 | L76: =K76 -> 28049 | M76: =L76 -> 28049 | N76: =M76 -> 28049 | O76: =N76 -> 28049 | P76: =O76 -> 28049
A77: Non-current Tax | B77: 0 | C77: 0 | D77: 0 | E77: 0 | F77: 0 | G77: 0 | H77: 0 | I77: 6055 | J77: 5838 | K77: =J77 -> 5838 | L77: =K77 -> 5838 | M77: =L77 -> 5838 | N77: =M77 -> 5838 | O77: =N77 -> 5838 | P77: =O77 -> 5838
A78: Deffered Tax | B78: 0 | C78: 0 | D78: 0 | E78: 0 | F78: 0 | G78: 5407 | H78: 25204 | I78: 2794 | J78: 467 | K78: =J78 -> 467 | L78: =K78 -> 467 | M78: =L78 -> 467 | N78: =M78 -> 467 | O78: =N78 -> 467 | P78: =O78 -> 467
A81: Current Assets | B81: =SUM(B83:B91) -> 79511 | C81: =SUM(C83:C91) -> 87980 | D81: =SUM(D83:D91) -> 79300 | E81: =SUM(E83:E91) -> 123727 | F81: =SUM(F83:F91) -> 84406 | G81: =SUM(G83:G91) -> 180970 | H81: =SUM(H83:H91) -> 167934 | I81: =SUM(I83:I91) -> 156692 | ... P81: =SUM(P83:P91) -> 2154103.7
A83: Inventories | B83: 31326 | C83: 32637 | D83: 31602 | E83: 33226 | F83: 32139 | G83: 30490 | H83: 35323 | I83: 54435 | J83: 53181 | K83: =K141 -> 65626.915 | L83: =L141 -> 76894.125 | M83: =M141 -> 90128.424 | N83: =N141 -> 105677.15 | O83: =O141 -> 123949.45 | P83: =P141 -> 145427.29
A84: Receivables | B84: 13234 | C84: 12026 | D84: 14654 | E84: 23128 | F84: 21298 | G84: 12799 | H84: 20345 | I84: 32848 | J84: 45968 | K84: =K142 -> 56725.861 | L84: =L142 -> 66464.887 | M84: =M142 -> 77904.202 | N84: =N142 -> 91344.04 | O84: =O142 -> 107138.05 | P84: =P142 -> 125702.82
A85: Cash & Bank Balances | B85: 507 | C85: 235 | D85: 740 | E85: 1878 | F85: 290 | G85: 30471 | H85: 30422 | I85: 27485 | J85: 28274 | K85: =K204 -> 233623.35 | L85: =L204 -> 426764.06 | M85: =M204 -> 660847.45 | N85: =N204 -> 943969.49 | O85: =O204 -> 1285658.1 | P85: =P204 -> 1697128
A86: Loans & Advances | B86: 31 | C86: 25 | D86: 30 | E86: 161 | F86: 170 | G86: 230 | H86: 305 | I86: 297 | J86: 327 | K86: =K143 -> 403.5276 | L86: =L143 -> 472.80756 | M86: =M143 -> 554.18278 | N86: =N143 -> 649.78901 | O86: =O143 -> 762.14194 | P86: =P143 -> 894.20517
A87: Other Current Assets | B87: 16611 | C87: 15408 | D87: 13140 | E87: 5638 | F87: 7974 | G87: 9581 | H87: 14608 | I87: 15602 | J87: 25077 | K87: =K144 -> 30945.754 | L87: =L144 -> 36258.701 | M87: =M144 -> 42499.21 | N87: =N144 -> 49831.067 | O87: =O144 -> 58447.197 | P87: =P144 -> 68574.872
A88: Current Tax Assets | B88: 4906 | C88: 4910 | D88: 4115 | E88: 4277 | F88: 5272 | G88: 0 | H88: 0 | I88: 0 | J88: 0 | K88: =K145 -> 0 | L88: =L145 -> 0 | M88: =M145 -> 0 | N88: =N145 -> 0 | O88: =O145 -> 0 | P88: =P145 -> 0
A89: Investment | B89: 11413 | C89: 21788 | D89: 12173 | E89: 50455 | F89: 12188 | G89: 84157 | H89: 41001 | I89: 0 | J89: 39122
A90: Other Financial Assets | B90: 1483 | C90: 951 | D90: 2846 | E90: 4964 | F90: 5075 | G90: 13242 | H90: 25930 | I90: 26025 | J90: 34186 | K90: =K146 -> 52517.155 | L90: =L146 -> 61533.605 | M90: =M146 -> 72124.195 | N90: =N146 -> 84566.88 | O90: =O146 -> 99189.068 | P90: =P146 -> 116376.46
A91: Assets Held for sale | B91: 0 | C91: 0 | D91: 0 | E91: 0 | F91: 0 | G91: 0 | H91: 0 | I91: 0 | J91: 203
A92: Total | B92: =B67+B81 -> 427255 | C92: =C67+C81 -> 519605 | D92: =D67+D81 -> 602484 | E92: =E67+E81 -> 639687 | F92: =F67+F81 -> 636277 | G92: =G67+G81 -> 713761 | H92: =H67+H81 -> 746555 | I92: =I67+I81 -> 1003854 | ... P92: =P67+P81 -> 3326163.2
A93: Balance sheet check >> | B93: =B92-B63 -> 0 | C93: =C92-C63 -> 0 | D93: =D92-D63 -> 0 | E93: =E92-E63 -> 0 | F93: =F92-F63 -> 0 | G93: =G92-G63 -> 0 | H93: =H92-H63 -> 0 | I93: =I92-I63 -> 0 | ... P93: =P92-P63 -> 0
A96: Capacity | B96: 1500000 | C96: 1550000 | D96: 1560000 | E96: 1580000 | F96: 2000000 | G96: 2250000 | H96: 2250000 | I96: 2250000 | J96: 2250000 | K96: =J96+K97 -> 2550000 | L96: =K96+L97 -> 2850000 | M96: =L96+M97 -> 3150000 | N96: =M96+N97 -> 3450000 | O96: =N96+O97 -> 3750000 | P96: =O96+P97 -> 4050000
A97: New Capacity | C97: =C96-B96 -> 50000 | D97: =D96-C96 -> 10000 | E97: =E96-D96 -> 20000 | F97: =F96-E96 -> 420000 | G97: =G96-F96 -> 250000 | H97: =H96-G96 -> 0 | I97: =I96-H96 -> 0 | J97: =J96-I96 -> 0 | K97: 300000 | L97: 300000 | M97: 300000 | N97: 300000 | O97: 300000 | P97: 300000
A99: Domestic | B99: 1305351 | C99: 1444541 | D99: 1653500 | E99: 1753700 | F99: 1461126 | G99: 1361722 | H99: 1414277 | I99: 1706831 | J99: 1852256
A100: Exports | B100: 123897 | C100: 124062 | D100: 126074 | E100: 108749 | F100: 102171 | G100: 96139 | H100: 238376 | I100: 259333 | J100: 283067
A101: Total | B101: =SUM(B99:B100) -> 1429248 | C101: =SUM(C99:C100) -> 1568603 | D101: =SUM(D99:D100) -> 1779574 | E101: =SUM(E99:E100) -> 1862449 | F101: =SUM(F99:F100) -> 1563297 | G101: =SUM(G99:G100) -> 1457861 | H101: =SUM(H99:H100) -> 1652653 | I101: =SUM(I99:I100) -> 1966164 | J101: =SUM(J99:J100) -> 2135323 | K101: =K114*K122 -> 2388726.8 | L101: =L114*L122 -> 2537202 | M101: =M114*M122 -> 2695883.2 | N101: =N114*N122 -> 2865482.9 | O101: =O114*O122 -> 3046763.4 | P101: =P114*P122 -> 3240540.5
A103: Capacity Utilization | B103: =B101/B96 -> 0.952832 | C103: =C101/C96 -> 1.0120019 | D103: =D101/D96 -> 1.1407526 | E103: =E101/E96 -> 1.1787652 | F103: =F101/F96 -> 0.7816485 | G103: =G101/G96 -> 0.64793822 | H103: =H101/H96 -> 0.73451244 | I103: =I101/I96 -> 0.87385067 | ... P103: =P101/P96 -> 0.80013345
A106: Growth in Domestic Sales | C106: =C99/B99-1 -> 0.10663032 | D106: =D99/C99-1 -> 0.14465425 | E106: =E99/D99-1 -> 0.06059873 | F106: =F99/E99-1 -> -0.16683241 | G106: =G99/F99-1 -> -0.068032463 | H106: =H99/G99-1 -> 0.038594515 | I106: =I99/H99-1 -> 0.20685764 | J106: =J99/I99-1 -> 0.085201757
A107: Growth in Export Sales | C107: =C100/B100-1 -> 0.0013317514 | D107: =D100/C100-1 -> 0.016217698 | E107: =E100/D100-1 -> -0.13741929 | F107: =F100/E100-1 -> -0.060487913 | G107: =G100/F100-1 -> -0.059038279 | H107: =H100/G100-1 -> 1.4794932 | I107: =I100/H100-1 -> 0.08791573 | J107: =J100/I100-1 -> 0.091519398
A108: Growth in total Sales | C108: =C101/B101-1 -> 0.097502323 | D108: =D101/C101-1 -> 0.13449611 | E108: =E101/D101-1 -> 0.046570134 | F108: =F101/E101-1 -> -0.16062292 | G108: =G101/F101-1 -> -0.067444638 | H108: =H101/G101-1 -> 0.13361493 | I108: =I101/H101-1 -> 0.18970165 | J108: =J101/I101-1 -> 0.086035041
A111: Industry Data
A112: Domestic Sales | B112: 2789208 | C112: 3047582 | D112: 3288581 | E112: 3377389 | F112: 2773519 | G112: 2711457 | H112: 3069523 | I112: 3890114 | J112: 4218746 | K112: =J112*(1+K115) -> 4514058.2 | L112: =K112*(1+L115) -> 4830042.3 | M112: =L112*(1+M115) -> 5168145.3 | N112: =M112*(1+N115) -> 5529915.4 | O112: =N112*(1+O115) -> 5917009.5 | P112: =O112*(1+P115) -> 6331200.2
A113: Exports | B113: 653053 | C113: 758727 | D113: 748366 | E113: 676192 | F113: 662118 | G113: 404397 | H113: 577875 | I113: 662891 | J113: 672105 | K113: =J113*(1+K116) -> 678826.05 | L113: =K113*(1+L116) -> 685614.31 | M113: =L113*(1+M116) -> 692470.45 | N113: =M113*(1+N116) -> 699395.16 | O113: =N113*(1+O116) -> 706389.11 | P113: =O113*(1+P116) -> 713453
A114: Total | B114: =SUM(B112:B113) -> 3442261 | C114: =SUM(C112:C113) -> 3806309 | D114: =SUM(D112:D113) -> 4036947 | E114: =SUM(E112:E113) -> 4053581 | F114: =SUM(F112:F113) -> 3435637 | G114: =SUM(G112:G113) -> 3115854 | H114: =SUM(H112:H113) -> 3647398 | I114: =SUM(I112:I113) -> 4553005 | ... P114: =SUM(P112:P113) -> 7044653.2
A115: Growth in Domestic Market | C115: =C112/B112-1 -> 0.092633464 | D115: =D112/C112-1 -> 0.079078758 | E115: =E112/D112-1 -> 0.02700496 | F115: =F112/E112-1 -> -0.17879788 | G115: =G112/F112-1 -> -0.022376627 | H115: =H112/G112-1 -> 0.13205668 | I115: =I112/H112-1 -> 0.26733502 | J115: =J112/I112-1 -> 0.084478758 | K115: 0.07 | L115: 0.07 | M115: 0.07 | N115: 0.07 | O115: 0.07 | P115: 0.07
A116: Growth on Export | C116: =C113/B113-1 -> 0.16181535 | D116: =D113/C113-1 -> -0.013655768 | E116: =E113/D113-1 -> -0.096442115 | F116: =F113/E113-1 -> -0.020813615 | G116: =G113/F113-1 -> -0.38923727 | H116: =H113/G113-1 -> 0.42897944 | I116: =I113/H113-1 -> 0.14711832 | J116: =J113/I113-1 -> 0.013899721 | K116: 0.01 | L116: 0.01 | M116: 0.01 | N116: 0.01 | O116: 0.01 | P116: 0.01
A119: Market Share
A120: Domestic | B120: =B99/B112 -> 0.46800059 | C120: =C99/C112 -> 0.47399578 | D120: =D99/D112 -> 0.50280045 | E120: =E99/E112 -> 0.51924726 | F120: =F99/F112 -> 0.52681305 | G120: =G99/G112 -> 0.50221044 | H120: =H99/H112 -> 0.46074814 | I120: =I99/I112 -> 0.43876118 | J120: =J99/J112 -> 0.43905369
A121: Exports | B121: =B100/B113 -> 0.18971967 | C121: =C100/C113 -> 0.16351336 | D121: =D100/D113 -> 0.1684657 | E121: =E100/E113 -> 0.16082562 | F121: =F100/F113 -> 0.15430935 | G121: =G100/G113 -> 0.23773421 | H121: =H100/H113 -> 0.41250443 | I121: =I100/I113 -> 0.39121515 | J121: =J100/J113 -> 0.42116485
A122: Overall | B122: =B101/B114 -> 0.41520617 | C122: =C101/C114 -> 0.41210606 | D122: =D101/D114 -> 0.44082174 | E122: =E101/E114 -> 0.4594577 | F122: =F101/F114 -> 0.45502392 | G122: =G101/G114 -> 0.46788489 | H122: =H101/H114 -> 0.45310465 | I122: =I101/I114 -> 0.43183875 | J122: =J101/J114 -> 0.43659539 | K122: 0.46 | L122: 0.46 | M122: 0.46 | N122: 0.46 | O122: 0.46 | P122: 0.46
A125: Revenue Per Car | B125: =(B5/B101)*1000000 -> 399241.42 | C125: =(C5/C101)*1000000 -> 434048.64 | D125: =(D5/D101)*1000000 -> 448474.75 | E125: =(E5/E101)*1000000 -> 462125.41 | F125: =(F5/F101)*1000000 -> 483977.13 | G125: =(G5/G101)*1000000 -> 482707.2 | H125: =(H5/H101)*1000000 -> 534472.75 | I125: =(I5/I101)*1000000 -> 602238.17 | J125: =(J5/J101)*1000000 -> 664340.71 | K125: =J125*(1+K126) -> 732847.25 | L125: =K125*(1+L126) -> 808418.14 | M125: =L125*(1+M126) -> 891781.88 | N125: =M125*(1+N126) -> 983742.05 | O125: =N125*(1+O126) -> 1085185.1 | P125: =O125*(1+P126) -> 1197089
A126: Growth | C126: =C125/B125-1 -> 0.087183393 | D126: =D125/C125-1 -> 0.033236152 | E126: =E125/D125-1 -> 0.030437965 | F126: =F125/E125-1 -> 0.047285275 | G126: =G125/F125-1 -> -0.0026239542 | H126: =H125/G125-1 -> 0.10724007 | I126: =I125/H125-1 -> 0.12678927 | J126: =J125/I125-1 -> 0.10311958 | K126: =J126 -> 0.10311958 | L126: =K126 -> 0.10311958 | M126: =L126 -> 0.10311958 | N126: =M126 -> 0.10311958 | O126: =N126 -> 0.10311958 | P126: =O126 -> 0.10311958
A128: Cost Drivers
A130: Raw Materials | B130: =B11/B5 -> 0.6344155 | C130: =C11/C5 -> 0.62609826 | D130: =D11/D5 -> 0.56313166 | E130: =E11/E5 -> 0.52313797 | F130: =F11/F5 -> 0.45776897 | G130: =G11/G5 -> 0.47314841 | H130: =H11/H5 -> 0.44990026 | I130: =I11/I5 -> 0.61947692 | J130: =J11/J5 -> 0.55629706 | K130: 0.6 | L130: 0.6 | M130: 0.6 | N130: 0.6 | O130: 0.6 | P130: 0.6
A131: Purchases | B131: =B12/B5 -> 0.055580383 | C131: =C12/C5 -> 0.065999853 | D131: =D12/D5 -> 0.12532484 | E131: =E12/E5 -> 0.16638956 | F131: =F12/F5 -> 0.24804652 | G131: =G12/G5 -> 0.24518416 | H131: =H12/H5 -> 0.29885158 | I131: =I12/I5 -> 0.10737869 | J131: =J12/J5 -> 0.14947462 | K131: 0.08 | L131: 0.08 | M131: 0.08 | N131: 0.08 | O131: 0.08 | P131: 0.08
A132: Changes in stock in trade | B132: =B13/B5 -> 0.00011040719 | C132: =C13/C5 -> -0.0055709775 | D132: =D13/D5 -> 0.00051121798 | E132: =E13/E5 -> 0.0024585069 | F132: =F13/F5 -> -0.0031430082 | G132: =G13/G5 -> 0.00388791 | H132: =H13/H5 -> -0.0010540044 | I132: =I13/I5 -> -0.0049024617 | J132: =J13/J5 -> -0.0026688623 | K132: =J132 -> -0.0026688623 | L132: =K132 -> -0.0026688623 | M132: =L132 -> -0.0026688623 | N132: =M132 -> -0.0026688623 | O132: =N132 -> -0.0026688623 | P132: =O132 -> -0.0026688623
A133: Employee Cost | B133: =B14/B5 -> 0.036104904 | C133: =C14/C5 -> 0.03466696 | D133: =D14/D5 -> 0.035877979 | E133: =E14/E5 -> 0.038167274 | F133: =F14/F5 -> 0.045151996 | G133: =G14/G5 -> 0.048763713 | H133: =H14/H5 -> 0.04586674 | I133: =I14/I5 -> 0.044831555 | J133: =J14/J5 -> 0.044421824 | K133: 0.04 | L133: 0.04 | M133: 0.04 | N133: 0.04 | O133: 0.04 | P133: 0.04
A134: Other Expenses | B134: =B15/B5 -> 0.14220972 | C134: =C15/C5 -> 0.1281927 | D134: =D15/D5 -> 0.12524339 | E134: =E15/E5 -> 0.14342297 | F134: =F15/F5 -> 0.15714512 | G134: =G15/G5 -> 0.15400301 | H134: =H15/H5 -> 0.14347027 | I134: =I15/I5 -> 0.12395163 | J134: =J15/J5 -> 0.1237158 | K134: 0.124 | L134: 0.124 | M134: 0.124 | N134: 0.124 | O134: 0.124 | P134: 0.124
A135: Own Uses Vehicles | B135: =B16/B5 -> -0.0010550021 | C135: =C16/C5 -> -0.0015216274 | D135: =D16/D5 -> -0.0012417084 | E135: =E16/E5 -> -0.0014186375 | F135: =F16/F5 -> -0.0016085118 | G135: =G16/G5 -> -0.0010345024 | H135: =H16/H5 -> -0.0016359145 | I135: =I16/I5 -> -0.00132168 | J135: =J16/J5 -> -0.0018377507 | K135: =J135 -> -0.0018377507 | L135: =K135 -> -0.0018377507 | M135: =L135 -> -0.0018377507 | N135: =M135 -> -0.0018377507 | O135: =N135 -> -0.0018377507 | P135: =O135 -> -0.0018377507
...

Sheet Dashboard
B2: Maruti Suzuki- Financial Ratio Dashboard (All Figures in ₹)
N40: Year | P40: Return on Equity | S40: Return on Asset
N42: 2025 | P42: ='Ratio''s'!G4 -> 0.17254717 | S42: ='Ratio''s'!H4 -> 0.12726537
N43: 2026 | P43: ='Ratio''s'!G5 -> 0.16790661 | S43: ='Ratio''s'!H5 -> 0.12522116
N44: 2027 | P44: ='Ratio''s'!G6 -> 0.16258708 | S44: ='Ratio''s'!H6 -> 0.12330163
N45: 2028 | P45: ='Ratio''s'!G7 -> 0.16110876 | S45: ='Ratio''s'!H6 -> 0.12330163
N46: 2029 | P46: ='Ratio''s'!G8 -> 0.16008486 | S46: ='Ratio''s'!H7 -> 0.12298234
N47: 2030 | P47: ='Ratio''s'!G9 -> 0.16343396 | S47: ='Ratio''s'!H8 -> 0.12289729

Sheet KPI'S
B3: Sum of Total Revenue | E3: Net profit margin | H3: Debt to EBITDA
B4: 13906105 | E4: 0.10317344 | H4: 0.12107814
B13: EBITDA Margin | E13: Return on Equity
B14: 0.16654348 | E14: 0.16343396 | H14: Interest Coverage Ratio
H15: 1.9862269

Sheet Free Cash Flow 
B3: Row Labels | C3: Sum of Cash flow
B4: 2025 | C4: 205349.35
B5: 2026 | C5: 193140.71
B6: 2028 | C6: 283122.04
B7: 2029 | C7: 341688.58
B8: 2030 | C8: 411469.95
B9: Grand Total | C9: 1434770.6

Sheet Revenue & EBITDA
B3: Row Labels | C3: Sum of Total Revenue | D3: EBITDA Margin
B4: 2025 | C4: 1770571.8 | D4: 0.16998935
B5: 2026 | C5: 2071120.2 | D5: 0.16861327
B6: 2028 | C6: 2838896 | D6: 0.16642084
B7: 2029 | C7: 3326302.3 | D7: 0.16555422
B8: 2030 | C8: 3899215.2 | D8: 0.16481257
B9: Grand Total | C9: 13906105 | D9: 0.16654348

Sheet Ratio's
B3: Row Labels | C3: Cash Ratio | D3: Current Ratio | F3: Row Labels | G3: Return on Equity | H3: Return on Assets
B4: 2025 | C4: 6.1908365 | D4: 1.3260297 | F4: 2025 | G4: 0.17254717 | H4: 0.12726537
B5: 2026 | C5: 4.9695683 | D5: 1.7197828 | F5: 2026 | G5: 0.16790661 | H5: 0.12522116
B6: 2028 | C6: 5.3006675 | D6: 2.3890247 | F6: 2028 | G6: 0.16258708 | H6: 0.12330163
B7: 2029 | C7: 5.4541094 | D7: 2.6739022 | F7: 2029 | G7: 0.16110876 | H7: 0.12298234
B8: 2030 | C8: 5.5979651 | D8: 2.9306143 | F8: 2030 | G8: 0.16008486 | H8: 0.12289729
B9: Grand Total | C9: 5.4846287 | D9: 2.3752112 | F9: Grand Total | G9: 0.16343396 | H9: 0.12386764
B16: Year | C16: EBITDA Margin | D16: Net profit margin | E16: Return on Equity | F16: Debt to EBITDA | G16: Interest Coverage Ratio | H16: Current Ratio
B17: 2025 | C17: 0.16998935 | D17: 0.10115659 | E17: 0.17254717 | F17: 0.12270945 | G17: 1.2435055 | H17: 1.3260297
B18: 2026 | C18: 0.16861327 | D18: 0.10137996 | E18: 0.16790661 | F18: 0.122066 | G18: 1.456075 | H18: 1.7197828
B19: 2028 | C19: 0.16642084 | D19: 0.10277413 | E19: 0.16258708 | F19: 0.12101884 | G19: 2.0194014 | H19: 2.3890247
B20: 2029 | C20: 0.16555422 | D20: 0.10375609 | E20: 0.16110876 | F20: 0.12059727 | G20: 2.3868878 | H20: 2.6739022
B21: 2030 | C21: 0.16481257 | D21: 0.10483557 | E21: 0.16008486 | F21: 0.12023298 | G21: 2.8252647 | H21: 2.9306143
B22: Grand Total | C22: 0.16654348 | D22: 0.10317344 | E22: 0.16343396 | F22: 0.12107814 | G22: 1.9862269 | H22: 2.3752112

Sheet ROE Trend
B3: Row Labels | C3: Return on Equity
B4: 2025 | C4: 0.17254717
B5: 2026 | C5: 0.16790661
B6: 2028 | C6: 0.16258708
B7: 2029 | C7: 0.16110876
B8: 2030 | C8: 0.16008486
B9: Grand Total | C9: 0.16343396

Sheet Debt vs EBITDA
B3: Row Labels | C3: Sum of Total Liabilites | D3: Sum of Operating Profit
B4: 2025 | C4: 369328.87 | D4: 300978.35
B5: 2026 | C5: 426276.86 | D5: 349218.35
B6: 2028 | C6: 571755.26 | D6: 472451.45
B7: 2029 | C7: 664109.14 | D7: 550683.38
B8: 2030 | C8: 772664.85 | D8: 642639.69
B9: Grand Total | C9: 2804135 | D9: 2315971.2

Sheet Revenue By Category
B3: Row Labels | C3: Sum of Total Revenue
B4: 2025 | C4: 1770571.8
B5: 2026 | C5: 2071120.2
B6: 2028 | C6: 2838896
B7: 2029 | C7: 3326302.3
B8: 2030 | C8: 3899215.2
B9: Grand Total | C9: 13906105

Sheet Sheet2
A1: Year | B1: Total Revenue | C1: Total Cost | D1: Operating Profit | E1: Depricition & Amortization | F1: EBIT | G1: Interest | H1: Profit Before Exceptional item | I1: Tax | J1: Net Profit | K1: Total Equity | L1: Total Current Liabilities | M1: Total Long term liabilities | N1: Total Liabilites | O1: Total Liability & Equity | P1: Total Current Asset | Q1: Total Long term Assets | R1: Total Asset | S1: Check | T1: Capacity | U1: New Capacity | V1: Working capital | W1: Capex Schedule | X1: Assets per Car | Y1: Cash flow
A2: 2025 | B2: ='Financial Statement '!K8 -> 1770571.8 | C2: ='Financial Statement '!K18 -> 1469593.5 | D2: =B2-C2 -> 300978.35 | E2: ='Financial Statement '!K22 -> 60235.688 | F2: =D2-E2 -> 240742.67 | G2: ='Financial Statement '!K26 -> 1936 | H2: =F2-G2 -> 238806.67 | I2: ='Financial Statement '!K32 -> 59701.667 | J2: =H2-I2 -> 179105 | K2: ='Financial Statement '!K41 -> 1038006 | L2: ='Financial Statement '!K55 -> 331698.87 | M2: ='Financial Statement '!K49 -> 37630 | N2: =L2+M2 -> 369328.87 | O2: =N2+K2 -> 1407334.9 | P2: ='Financial Statement '!K81 -> 439842.56 | Q2: ='Financial Statement '!K67 -> 967492.31 | R2: =P2+Q2 -> 1407334.9 | S2: =R2-O2 -> 0 | T2: ='Financial Statement '!K96 -> 2550000 | U2: ='Financial Statement '!K97 -> 300000 | V2: =P2-L2 -> 108143.69 | W2: ='Financial Statement '!K189 -> 100558 | X2: ='Financial Statement '!K185 -> 160000 | Y2: ='Financial Statement '!K203 -> 205349.35
A3: 2026 | B3: ='Financial Statement '!L8 -> 2071120.2 | C3: ='Financial Statement '!L18 -> 1721901.8 | D3: =B3-C3 -> 349218.35 | E3: ='Financial Statement '!L22 -> 67322.24 | F3: =D3-E3 -> 281896.11 | G3: ='Financial Statement '!L26 -> 1936 | H3: =F3-G3 -> 279960.11 | I3: ='Financial Statement '!L32 -> 69990.028 | J3: =H3-I3 -> 209970.08 | K3: ='Financial Statement '!L41 -> 1250517.1 | L3: ='Financial Statement '!L55 -> 388646.86 | M3: ='Financial Statement '!L49 -> 37630 | N3: =L3+M3 -> 426276.86 | O3: =N3+K3 -> 1676793.9 | P3: ='Financial Statement '!L81 -> 668388.19 | Q3: ='Financial Statement '!L67 -> 1008405.8 | R3: =P3+Q3 -> 1676793.9 | S3: =R3-O3 -> 0 | T3: ='Financial Statement '!L96 -> 2850000 | U3: =T3-T2 -> 300000 | V3: =P3-L3 -> 279741.32 | W3: ='Financial Statement '!L189 -> 108235.69 | X3: ='Financial Statement '!L185 -> 160000 | Y3: ='Financial Statement '!L203 -> 193140.71
A4: 2027 | B4: ='Financial Statement '!M8 -> 2424139.8 | C4: ='Financial Statement '!M18 -> 2018259.5 | D4: =B4-C4 -> 405880.34 | E4: ='Financial Statement '!M22 -> 74408.791 | F4: =D4-E4 -> 331471.55 | G4: ='Financial Statement '!M26 -> 1936 | H4: =F4-G4 -> 329535.55 | I4: ='Financial Statement '!M32 -> 82383.887 | J4: =H4-I4 -> 247151.66 | K4: ='Financial Statement '!M41 -> 1500209.7 | L4: ='Financial Statement '!M55 -> 455537.13 | M4: ='Financial Statement '!M49 -> 37630 | N4: =L4+M4 -> 493167.13 | O4: =N4+K4 -> 1993376.9 | P4: ='Financial Statement '!M81 -> 944057.67 | Q4: ='Financial Statement '!M67 -> 1049319.2 | R4: =P4+Q4 -> 1993376.9 | S4: =R4-O4 -> 0 | T4: ='Financial Statement '!M96 -> 3150000 | U4: =T4-T3 -> 300000 | V4: =P4-L4 -> 488520.54 | W4: ='Financial Statement '!M189 -> 115322.24 | X4: ='Financial Statement '!M185 -> 160000 | Y4: ='Financial Statement '!M203 -> 234083.39
A5: 2028 | B5: ='Financial Statement '!N8 -> 2838896 | C5: ='Financial Statement '!N18 -> 2366444.6 | D5: =B5-C5 -> 472451.45 | E5: ='Financial Statement '!N22 -> 81495.343 | F5: =D5-E5 -> 390956.11 | G5: ='Financial Statement '!N26 -> 1936 | H5: =F5-G5 -> 389020.11 | I5: ='Financial Statement '!N32 -> 97255.027 | J5: =H5-I5 -> 291765.08 | K5: ='Financial Statement '!N41 -> 1794515.8 | L5: ='Financial Statement '!N55 -> 534125.26 | M5: ='Financial Statement '!N49 -> 37630 | N5: =L5+M5 -> 571755.26 | O5: =N5+K5 -> 2366271.1 | P5: ='Financial Statement '!N81 -> 1276038.4 | Q5: ='Financial Statement '!N67 -> 1090232.7 | R5: =P5+Q5 -> 2366271.1 | S5: =R5-O5 -> 0 | T5: ='Financial Statement '!N96 -> 3450000 | U5: =T5-T4 -> 300000 | V5: =P5-L5 -> 741913.17 | W5: ='Financial Statement '!N189 -> 122408.79 | X5: ='Financial Statement '!N185 -> 160000 | Y5: ='Financial Statement '!N203 -> 283122.04
A6: 2029 | B6: ='Financial Statement '!O8 -> 3326302.3 | C6: ='Financial Statement '!O18 -> 2775618.9 | D6: =B6-C6 -> 550683.38 | E6: ='Financial Statement '!O22 -> 88581.894 | F6: =D6-E6 -> 462101.48 | G6: ='Financial Statement '!O26 -> 1936 | H6: =F6-G6 -> 460165.48 | I6: ='Financial Statement '!O32 -> 115041.37 | J6: =H6-I6 -> 345124.11 | K6: ='Financial Statement '!O41 -> 2142180.9 | L6: ='Financial Statement '!O55 -> 626479.14 | M6: ='Financial Statement '!O49 -> 37630 | N6: =L6+M6 -> 664109.14 | O6: =N6+K6 -> 2806290.1 | P6: ='Financial Statement '!O81 -> 1675144 | Q6: ='Financial Statement '!O67 -> 1131146.1 | R6: =P6+Q6 -> 2806290.1 | S6: =R6-O6 -> 0 | T6: ='Financial Statement '!O96 -> 3750000 | U6: =T6-T5 -> 300000 | V6: =P6-L6 -> 1048664.8 | W6: ='Financial Statement '!O189 -> 129495.34 | X6: ='Financial Statement '!O185 -> 160000 | Y6: ='Financial Statement '!O203 -> 341688.58
A7: 2030 | B7: ='Financial Statement '!P8 -> 3899215.2 | C7: ='Financial Statement '!P18 -> 3256575.5 | D7: =B7-C7 -> 642639.69 | E7: ='Financial Statement '!P22 -> 95668.446 | F7: =D7-E7 -> 546971.24 | G7: ='Financial Statement '!P26 -> 1936 | H7: =F7-G7 -> 545035.24 | I7: ='Financial Statement '!P32 -> 136258.81 | J7: =H7-I7 -> 408776.43 | K7: ='Financial Statement '!P41 -> 2553498.4 | L7: ='Financial Statement '!P55 -> 735034.85 | M7: ='Financial Statement '!P49 -> 37630 | N7: =L7+M7 -> 772664.85 | O7: =N7+K7 -> 3326163.2 | P7: ='Financial Statement '!P81 -> 2154103.7 | Q7: ='Financial Statement '!P67 -> 1172059.6 | R7: =P7+Q7 -> 3326163.2 | S7: =R7-O7 -> 0 | T7: ='Financial Statement '!P96 -> 4050000 | U7: =T7-T6 -> 300000 | V7: =P7-L7 -> 1419068.8 | W7: ='Financial Statement '!P189 -> 136581.89 | X7: ='Financial Statement '!P185 -> 160000 | Y7: ='Financial Statement '!P203 -> 411469.95
A15: Year
A16: 2025
A17: 2026
A18: 2027
A19: 2028
A20: 2029
A21: 2030
